{
  "24f241e1-fb35-4965-8c8b-357b6db1b2a6": {
    "connectionParameters": {
      "sku": "Enterprise"
    },
    "connectionRef": {
      "apiTier": "Standard",
      "displayName": "Power Platform for Admins",
      "iconUri": "https://connectoricons-prod.azureedge.net/releases/v1.0.1566/1.0.1566.2741/powerplatformforadmins/icon.png",
      "id": "/providers/microsoft.powerapps/apis/shared_powerplatformforadmins",
      "parameterHints": {},
      "parameterHintsV2": {}
    },
    "datasets": {},
    "dataSources": [
      "PowerPlatformforAdmins"
    ],
    "dependencies": {},
    "dependents": [],
    "id": "24f241e1-fb35-4965-8c8b-357b6db1b2a6"
  },
  "9b042c2a-7f23-42eb-999b-489d3f713e4b": {
    "connectionParameters": {
      "sku": "Enterprise"
    },
    "connectionRef": {
      "apiTier": "Standard",
      "displayName": "Office 365 Groups",
      "iconUri": "https://connectoricons-prod.azureedge.net/releases/v1.0.1563/1.0.1563.2732/office365groups/icon.png",
      "id": "/providers/microsoft.powerapps/apis/shared_office365groups",
      "parameterHints": {},
      "parameterHintsV2": {}
    },
    "datasets": {},
    "dataSources": [
      "Office365Groups"
    ],
    "dependencies": {},
    "dependents": [],
    "id": "9b042c2a-7f23-42eb-999b-489d3f713e4b"
  },
  "ae400b4b-90af-4d98-88bc-9df80776878c": {
    "connectionParameters": {
      "sku": "Enterprise"
    },
    "connectionRef": {
      "apiTier": "Standard",
      "displayName": "Office 365 Users",
      "iconUri": "https://connectoricons-prod.azureedge.net/releases/v1.0.1559/1.0.1559.2723/office365users/icon.png",
      "id": "/providers/microsoft.powerapps/apis/shared_office365users",
      "parameterHints": {},
      "parameterHintsV2": {}
    },
    "datasets": {},
    "dataSources": [
      "Office365Users"
    ],
    "dependencies": {},
    "dependents": [],
    "id": "ae400b4b-90af-4d98-88bc-9df80776878c"
  },
  "fca84456-c98f-49f7-9f89-552359b29e63": {
    "connectionParameters": {
      "sku": "Enterprise"
    },
    "connectionRef": {
      "apiTier": "Standard",
      "displayName": "Power Apps for Makers",
      "iconUri": "https://connectoricons-prod.azureedge.net/releases/v1.0.1551/1.0.1551.2693/powerappsforappmakers/icon.png",
      "id": "/providers/microsoft.powerapps/apis/shared_powerappsforappmakers",
      "parameterHints": {},
      "parameterHintsV2": {}
    },
    "datasets": {},
    "dataSources": [
      "PowerAppsforMakers"
    ],
    "dependencies": {},
    "dependents": [],
    "id": "fca84456-c98f-49f7-9f89-552359b29e63"
  }
}