<?xml version="1.0" encoding="utf-8"?>
<ImportExportXml xmlns:xsi="http://www.w3.org/2001/XMLSchema-instance">
  <Entities />
  <Roles />
  <Workflows />
  <FieldSecurityProfiles />
  <Templates />
  <EntityMaps />
  <EntityRelationships />
  <OrganizationSettings />
  <optionsets />
  <CustomControls />
  <EntityDataProviders />
  <connectionreferences>
    <connectionreference connectionreferencelogicalname="admin_sharedadmin5foffice2036520management20api5f691c36f6fa56d15c_faecd">
      <connectionreferencedisplayname>Office 365 Management API</connectionreferencedisplayname>
      <connectorid>/providers/Microsoft.PowerApps/apis/shared_admin-5foffice-20365-20management-20api-5f691c36f6fa56d15c</connectorid>
      <customconnectorid>
        <connectorid>de4da0c8-bd02-41df-b0da-bbe0290e8fb4</connectorid>
      </customconnectorid>
      <iscustomizable>1</iscustomizable>
      <statecode>0</statecode>
      <statuscode>1</statuscode>
    </connectionreference>
    <connectionreference connectionreferencelogicalname="admin_sharedadmin5foffice2036520management20api5f691c36f6fa56d15c_4a1b8">
      <connectionreferencedisplayname>Office 365 Management API</connectionreferencedisplayname>
      <connectorid>/providers/Microsoft.PowerApps/apis/shared_admin-5foffice-20365-20management-20api-5f691c36f6fa56d15c</connectorid>
      <customconnectorid>
        <connectorid>de4da0c8-bd02-41df-b0da-bbe0290e8fb4</connectorid>
      </customconnectorid>
      <iscustomizable>1</iscustomizable>
      <statecode>0</statecode>
      <statuscode>1</statuscode>
    </connectionreference>
  </connectionreferences>
  <Languages>
    <Language>1033</Language>
  </Languages>
</ImportExportXml>