{
  "13855a72-9d6b-4c7e-b05a-47e78bc695c1": {
    "appActions": [
      "Run"
    ],
    "connectionRef": {
      "apiTier": "Standard",
      "displayName": "Logic flows",
      "iconUri": "https://connectoricons-prod.azureedge.net/releases/v1.0.1680/1.0.1680.3652/logicflows/icon.png",
      "id": "/providers/microsoft.powerapps/apis/shared_logicflows",
      "parameterHints": {
        "3ff88cb5-3509-4006-aecd-65b396304f7f": {
          "value": "shared_commondataserviceforapps"
        },
        "8f9ab2bb-17a3-4a1e-9c45-da5dd25b2201": {
          "value": "shared_office365"
        },
        "e8119579-f194-42b5-8640-349f06002d39": {
          "value": "shared_office365users"
        },
        "workflowDisplayName": {
          "value": "HELPER - Get Connections to Clean"
        },
        "workflowEntityId": {
          "value": "4d38705e-20db-ee11-904d-000d3a3411d9"
        },
        "workflowName": {
          "value": "181597bb-5319-a427-c283-49654ad0f329"
        }
      },
      "parameterHintsV2": {
        "shared_commondataserviceforapps": {
          "value": "3ff88cb5-3509-4006-aecd-65b396304f7f"
        },
        "shared_office365": {
          "value": "8f9ab2bb-17a3-4a1e-9c45-da5dd25b2201"
        },
        "shared_office365users": {
          "value": "e8119579-f194-42b5-8640-349f06002d39"
        },
        "workflowDisplayName": {
          "value": "HELPER - Get Connections to Clean"
        },
        "workflowEntityId": {
          "value": "4d38705e-20db-ee11-904d-000d3a3411d9"
        },
        "workflowName": {
          "value": "181597bb-5319-a427-c283-49654ad0f329"
        }
      }
    },
    "datasets": {},
    "dataSources": [
      "HELPER-GetConnectionstoClean"
    ],
    "dependencies": {
      "shared_commondataserviceforapps": "3ff88cb5-3509-4006-aecd-65b396304f7f",
      "shared_office365": "8f9ab2bb-17a3-4a1e-9c45-da5dd25b2201",
      "shared_office365users": "e8119579-f194-42b5-8640-349f06002d39"
    },
    "dependents": [],
    "id": "13855a72-9d6b-4c7e-b05a-47e78bc695c1"
  },
  "3ff88cb5-3509-4006-aecd-65b396304f7f": {
    "appActions": [],
    "connectionRef": {
      "apiTier": "Premium",
      "bypassConsent": true,
      "displayName": "Microsoft Dataverse",
      "iconUri": "https://connectoricons-prod.azureedge.net/releases/v1.0.1679/1.0.1679.3643/commondataserviceforapps/icon.png",
      "id": "/providers/microsoft.powerapps/apis/shared_commondataserviceforapps",
      "parameterHints": {},
      "parameterHintsV2": {}
    },
    "datasets": {},
    "dataSources": [],
    "dependencies": {},
    "dependents": [
      "fe4d2439-b962-46e6-8728-85fee5bef7cb",
      "13855a72-9d6b-4c7e-b05a-47e78bc695c1"
    ],
    "id": "3ff88cb5-3509-4006-aecd-65b396304f7f"
  },
  "8bcdeee0-24d8-4ebb-b7dc-ed3cade44f2a": {
    "appActions": [],
    "connectionRef": {
      "apiTier": "Standard",
      "displayName": "Power Apps for Admins",
      "iconUri": "https://connectoricons-prod.azureedge.net/releases/v1.0.1669/1.0.1669.3520/powerappsforadmins/icon.png",
      "id": "/providers/microsoft.powerapps/apis/shared_powerappsforadmins",
      "parameterHints": {},
      "parameterHintsV2": {}
    },
    "datasets": {},
    "dataSources": [
      "PowerAppsforAdmins"
    ],
    "dependencies": {},
    "dependents": [],
    "id": "8bcdeee0-24d8-4ebb-b7dc-ed3cade44f2a"
  },
  "8f9ab2bb-17a3-4a1e-9c45-da5dd25b2201": {
    "appActions": [],
    "connectionRef": {
      "apiTier": "Standard",
      "displayName": "Office 365 Outlook",
      "iconUri": "https://connectoricons-prod.azureedge.net/releases/v1.0.1677/1.0.1677.3637/office365/icon.png",
      "id": "/providers/microsoft.powerapps/apis/shared_office365",
      "parameterHints": {},
      "parameterHintsV2": {}
    },
    "datasets": {},
    "dataSources": [],
    "dependencies": {},
    "dependents": [
      "13855a72-9d6b-4c7e-b05a-47e78bc695c1"
    ],
    "id": "8f9ab2bb-17a3-4a1e-9c45-da5dd25b2201"
  },
  "e8119579-f194-42b5-8640-349f06002d39": {
    "appActions": [],
    "connectionRef": {
      "apiTier": "Standard",
      "displayName": "Office 365 Users",
      "iconUri": "https://connectoricons-prod.azureedge.net/releases/v1.0.1677/1.0.1677.3637/office365users/icon.png",
      "id": "/providers/microsoft.powerapps/apis/shared_office365users",
      "parameterHints": {},
      "parameterHintsV2": {}
    },
    "datasets": {},
    "dataSources": [],
    "dependencies": {},
    "dependents": [
      "13855a72-9d6b-4c7e-b05a-47e78bc695c1"
    ],
    "id": "e8119579-f194-42b5-8640-349f06002d39"
  },
  "fe4d2439-b962-46e6-8728-85fee5bef7cb": {
    "appActions": [
      "Run"
    ],
    "connectionRef": {
      "apiTier": "Standard",
      "displayName": "Logic flows",
      "iconUri": "https://connectoricons-prod.azureedge.net/releases/v1.0.1680/1.0.1680.3652/logicflows/icon.png",
      "id": "/providers/microsoft.powerapps/apis/shared_logicflows",
      "parameterHints": {
        "3ff88cb5-3509-4006-aecd-65b396304f7f": {
          "value": "shared_commondataserviceforapps"
        },
        "workflowDisplayName": {
          "value": "HELPER - Delete Connection"
        },
        "workflowEntityId": {
          "value": "bd70d840-c4db-ee11-904d-000d3a341fff"
        },
        "workflowName": {
          "value": "159bcf5c-b002-842f-323a-58a384233ba8"
        }
      },
      "parameterHintsV2": {
        "shared_commondataserviceforapps": {
          "value": "3ff88cb5-3509-4006-aecd-65b396304f7f"
        },
        "workflowDisplayName": {
          "value": "HELPER - Delete Connection"
        },
        "workflowEntityId": {
          "value": "bd70d840-c4db-ee11-904d-000d3a341fff"
        },
        "workflowName": {
          "value": "159bcf5c-b002-842f-323a-58a384233ba8"
        }
      }
    },
    "datasets": {},
    "dataSources": [
      "HELPER-DeleteConnection"
    ],
    "dependencies": {
      "shared_commondataserviceforapps": "3ff88cb5-3509-4006-aecd-65b396304f7f"
    },
    "dependents": [],
    "id": "fe4d2439-b962-46e6-8728-85fee5bef7cb"
  }
}