[
  {
    "Data": "[{\"metaArea\":\"Inventory\",\"metaFlows\":\"Admin | Broken Connection Cleanup\",\"metaName\":\"Admin eMail\",\"metaOrder\":1,\"metaSolution\":\"Core\",\"metaType\":\"EnvironmentVariable\"},{\"metaArea\":\"Inventory\",\"metaFlows\":\"Admin | Capacity Alerts\",\"metaName\":\"Admin eMail\",\"metaOrder\":2,\"metaSolution\":\"Core\",\"metaType\":\"EnvironmentVariable\"},{\"metaArea\":\"Inventory\",\"metaFlows\":\"Admin | Compliance detail request v3\",\"metaName\":\"Admin eMail\",\"metaOrder\":3,\"metaSolution\":\"Core\",\"metaType\":\"EnvironmentVariable\"},{\"metaArea\":\"Inventory\",\"metaFlows\":\"Admin | Compliance Details Request eMail (Apps)\",\"metaName\":\"Admin eMail\",\"metaOrder\":4,\"metaSolution\":\"Core\",\"metaType\":\"EnvironmentVariable\"},{\"metaArea\":\"Inventory\",\"metaFlows\":\"Admin | Compliance Details Request eMail (Chatbots)\",\"metaName\":\"Admin eMail\",\"metaOrder\":5,\"metaSolution\":\"Core\",\"metaType\":\"EnvironmentVariable\"},{\"metaArea\":\"Inventory\",\"metaFlows\":\"Admin | Compliance Details Request eMail (Custom Connectors)\",\"metaName\":\"Admin eMail\",\"metaOrder\":6,\"metaSolution\":\"Core\",\"metaType\":\"EnvironmentVariable\"},{\"metaArea\":\"Inventory\",\"metaFlows\":\"Admin | Compliance Details Request eMail (Desktop Flows)\",\"metaName\":\"Admin eMail\",\"metaOrder\":7,\"metaSolution\":\"Core\",\"metaType\":\"EnvironmentVariable\"},{\"metaArea\":\"Inventory\",\"metaFlows\":\"Admin | Compliance Details Request eMail (Flows)\",\"metaName\":\"Admin eMail\",\"metaOrder\":8,\"metaSolution\":\"Core\",\"metaType\":\"EnvironmentVariable\"},{\"metaArea\":\"Inventory\",\"metaFlows\":\"Admin | Email Managers Ignored Inactivity notifications Approvals\",\"metaName\":\"Admin eMail\",\"metaOrder\":9,\"metaSolution\":\"Core\",\"metaType\":\"EnvironmentVariable\"},{\"metaArea\":\"Inventory\",\"metaFlows\":\"Admin | Inactivity notifications v2 (Check Approval)\",\"metaName\":\"Admin eMail\",\"metaOrder\":10,\"metaSolution\":\"Core\",\"metaType\":\"EnvironmentVariable\"},{\"metaArea\":\"Inventory\",\"metaFlows\":\"Admin | Inactivity notifications v2 (Clean Up and Delete)\",\"metaName\":\"Admin eMail\",\"metaOrder\":11,\"metaSolution\":\"Core\",\"metaType\":\"EnvironmentVariable\"},{\"metaArea\":\"Inventory\",\"metaFlows\":\"Admin | Inactivity notifications v2 (Start Approval for Apps)\",\"metaName\":\"Admin eMail\",\"metaOrder\":12,\"metaSolution\":\"Core\",\"metaType\":\"EnvironmentVariable\"},{\"metaArea\":\"Inventory\",\"metaFlows\":\"Admin | Inactivity notifications v2 (Start Approval for Flows)\",\"metaName\":\"Admin eMail\",\"metaOrder\":13,\"metaSolution\":\"Core\",\"metaType\":\"EnvironmentVariable\"},{\"metaArea\":\"Inventory\",\"metaFlows\":\"Admin | Newsletter with Product Updates\",\"metaName\":\"Admin eMail\",\"metaOrder\":14,\"metaSolution\":\"Core\",\"metaType\":\"EnvironmentVariable\"},{\"metaArea\":\"Inventory\",\"metaFlows\":\"Admin | Set app quarantine status\",\"metaName\":\"Admin eMail\",\"metaOrder\":15,\"metaSolution\":\"Core\",\"metaType\":\"EnvironmentVariable\"},{\"metaArea\":\"Inventory\",\"metaFlows\":\"Admin | Sync Template v3 (Connection Identities)\",\"metaName\":\"Admin eMail\",\"metaOrder\":16,\"metaSolution\":\"Core\",\"metaType\":\"EnvironmentVariable\"},{\"metaArea\":\"Inventory\",\"metaFlows\":\"Admin | Sync Template v3 (Sync Flow Errors)\",\"metaName\":\"Admin eMail\",\"metaOrder\":17,\"metaSolution\":\"Core\",\"metaType\":\"EnvironmentVariable\"},{\"metaArea\":\"Inventory\",\"metaFlows\":\"Admin | Welcome Email v3\",\"metaName\":\"Admin eMail\",\"metaOrder\":18,\"metaSolution\":\"Core\",\"metaType\":\"EnvironmentVariable\"},{\"metaArea\":\"Inventory\",\"metaFlows\":\"Env Request | Cleanup environments\",\"metaName\":\"Admin eMail\",\"metaOrder\":19,\"metaSolution\":\"Core\",\"metaType\":\"EnvironmentVariable\"},{\"metaArea\":\"Inventory\",\"metaFlows\":\"Env Request | Cleanup expired environments\",\"metaName\":\"Admin eMail\",\"metaOrder\":20,\"metaSolution\":\"Core\",\"metaType\":\"EnvironmentVariable\"},{\"metaArea\":\"Inventory\",\"metaFlows\":\"Env Request | Create approved environment\",\"metaName\":\"Admin eMail\",\"metaOrder\":21,\"metaSolution\":\"Core\",\"metaType\":\"EnvironmentVariable\"},{\"metaArea\":\"Inventory\",\"metaFlows\":\"Env Request | Notify admin when new request submitted\",\"metaName\":\"Admin eMail\",\"metaOrder\":22,\"metaSolution\":\"Core\",\"metaType\":\"EnvironmentVariable\"},{\"metaArea\":\"Inventory\",\"metaFlows\":\"Env Request | Notify requestor when rejected\",\"metaName\":\"Admin eMail\",\"metaOrder\":23,\"metaSolution\":\"Core\",\"metaType\":\"EnvironmentVariable\"},{\"metaArea\":\"Inventory\",\"metaFlows\":\"Microsoft Teams Admin |Weekly Clean Up of Microsoft Teams environments\",\"metaName\":\"Admin eMail\",\"metaOrder\":24,\"metaSolution\":\"Core\",\"metaType\":\"EnvironmentVariable\"},{\"metaArea\":\"Inventory\",\"metaFlows\":\"Microsoft Teams Admin | Ask for Business Justification when Microsoft Teams environment is created\",\"metaName\":\"Admin eMail\",\"metaOrder\":25,\"metaSolution\":\"Core\",\"metaType\":\"EnvironmentVariable\"},{\"metaArea\":\"Inventory\",\"metaFlows\":\"Microsoft Teams Admin | Send Reminder Mail\",\"metaName\":\"Admin eMail\",\"metaOrder\":26,\"metaSolution\":\"Core\",\"metaType\":\"EnvironmentVariable\"},{\"metaArea\":\"Inventory\",\"metaFlows\":\"Request Orphaned Objects Reassigned (Child)\",\"metaName\":\"Admin eMail\",\"metaOrder\":27,\"metaSolution\":\"Core\",\"metaType\":\"EnvironmentVariable\"},{\"metaArea\":\"Inventory\",\"metaFlows\":\"Request Orphaned Objects Reassigned (Parent)\",\"metaName\":\"Admin eMail\",\"metaOrder\":28,\"metaSolution\":\"Core\",\"metaType\":\"EnvironmentVariable\"},{\"metaArea\":\"Inventory\",\"metaFlows\":\"Training In A Day | Feedback Reminder\",\"metaName\":\"Admin eMail\",\"metaOrder\":29,\"metaSolution\":\"Core\",\"metaType\":\"EnvironmentVariable\"},{\"metaArea\":\"Inventory\",\"metaFlows\":\"Training In A Day | Registration Confirmation\",\"metaName\":\"Admin eMail\",\"metaOrder\":30,\"metaSolution\":\"Core\",\"metaType\":\"EnvironmentVariable\"},{\"metaArea\":\"Inventory\",\"metaFlows\":\"Training In A Day | Reminder 3 days prior event\",\"metaName\":\"Admin eMail\",\"metaOrder\":31,\"metaSolution\":\"Core\",\"metaType\":\"EnvironmentVariable\"},{\"metaArea\":\"Compliance\",\"metaFlows\":\"Admin | Compliance detail request v3\",\"metaName\":\"Compliance \\u2013 Apps \\u2013 Number Days Since Published\",\"metaOrder\":1,\"metaSolution\":\"Core\",\"metaType\":\"EnvironmentVariable\"},{\"metaArea\":\"Compliance\",\"metaFlows\":\"Admin | Compliance detail request v3\",\"metaName\":\"Compliance \\u2013 Apps \\u2013 Number Groups Shared\",\"metaOrder\":1,\"metaSolution\":\"Core\",\"metaType\":\"EnvironmentVariable\"},{\"metaArea\":\"Compliance\",\"metaFlows\":\"Admin | Compliance detail request v3\",\"metaName\":\"Compliance \\u2013 Apps \\u2013 Number Launches Last 30 Days\",\"metaOrder\":1,\"metaSolution\":\"Core\",\"metaType\":\"EnvironmentVariable\"},{\"metaArea\":\"Compliance\",\"metaFlows\":\"Admin | Compliance detail request v3\",\"metaName\":\"Compliance \\u2013 Apps - Number Users Shared\",\"metaOrder\":1,\"metaSolution\":\"Core\",\"metaType\":\"EnvironmentVariable\"},{\"metaArea\":\"Compliance\",\"metaFlows\":\"Admin | Compliance detail request v3\",\"metaName\":\"Compliance \\u2013 Chatbots \\u2013 Number Launches\",\"metaOrder\":1,\"metaSolution\":\"Core\",\"metaType\":\"EnvironmentVariable\"},{\"metaArea\":\"Inventory\",\"metaFlows\":\"Admin | Sync Template v3\",\"metaName\":\"DelayInventory\",\"metaOrder\":1,\"metaSolution\":\"Core\",\"metaType\":\"EnvironmentVariable\"},{\"metaArea\":\"Compliance\",\"metaFlows\":\"Admin | Compliance detail request v3\",\"metaName\":\"Developer Compliance Center URL\",\"metaOrder\":1,\"metaSolution\":\"Core\",\"metaType\":\"EnvironmentVariable\"},{\"metaArea\":\"Compliance\",\"metaFlows\":\"Admin | Set app quarantine status\",\"metaName\":\"Developer Compliance Center URL\",\"metaOrder\":2,\"metaSolution\":\"Core\",\"metaType\":\"EnvironmentVariable\"},{\"metaArea\":\"Compliance\",\"metaFlows\":\"Admin | Compliance Details Request eMail (Apps)\",\"metaName\":\"Developer Compliance Center URL\",\"metaOrder\":3,\"metaSolution\":\"Core\",\"metaType\":\"EnvironmentVariable\"},{\"metaArea\":\"Compliance\",\"metaFlows\":\"Admin | Compliance Details Request eMail (Chatbots)\",\"metaName\":\"Developer Compliance Center URL\",\"metaOrder\":4,\"metaSolution\":\"Core\",\"metaType\":\"EnvironmentVariable\"},{\"metaArea\":\"Compliance\",\"metaFlows\":\"Admin | Compliance Details Request eMail (Custom Connectors)\",\"metaName\":\"Developer Compliance Center URL\",\"metaOrder\":5,\"metaSolution\":\"Core\",\"metaType\":\"EnvironmentVariable\"},{\"metaArea\":\"Compliance\",\"metaFlows\":\"Admin | Compliance Details Request eMail (Desktop Flows)\",\"metaName\":\"Developer Compliance Center URL\",\"metaOrder\":6,\"metaSolution\":\"Core\",\"metaType\":\"EnvironmentVariable\"},{\"metaArea\":\"Compliance\",\"metaFlows\":\"Admin | Compliance Details Request eMail (Flows)\",\"metaName\":\"Developer Compliance Center URL\",\"metaOrder\":7,\"metaSolution\":\"Core\",\"metaType\":\"EnvironmentVariable\"},{\"metaArea\":\"Inventory\",\"metaFlows\":\"Admin | Sync Template v3 (Ai Models)\",\"metaName\":\"FullInventory\",\"metaOrder\":1,\"metaSolution\":\"Core\",\"metaType\":\"EnvironmentVariable\"},{\"metaArea\":\"Inventory\",\"metaFlows\":\"Admin | Sync Template v3 (Apps)\",\"metaName\":\"FullInventory\",\"metaOrder\":2,\"metaSolution\":\"Core\",\"metaType\":\"EnvironmentVariable\"},{\"metaArea\":\"Inventory\",\"metaFlows\":\"Admin | Sync Template v3 (Business Process Flows)\",\"metaName\":\"FullInventory\",\"metaOrder\":3,\"metaSolution\":\"Core\",\"metaType\":\"EnvironmentVariable\"},{\"metaArea\":\"Inventory\",\"metaFlows\":\"Admin | Sync Template v3 (Flows)\",\"metaName\":\"FullInventory\",\"metaOrder\":4,\"metaSolution\":\"Core\",\"metaType\":\"EnvironmentVariable\"},{\"metaArea\":\"Inventory\",\"metaFlows\":\"Admin | Sync Template v3 (Desktop flows)\",\"metaName\":\"FullInventory\",\"metaOrder\":5,\"metaSolution\":\"Core\",\"metaType\":\"EnvironmentVariable\"},{\"metaArea\":\"Inventory\",\"metaFlows\":\"Admin | Sync Template v3 (Model Driven Apps)\",\"metaName\":\"FullInventory\",\"metaOrder\":6,\"metaSolution\":\"Core\",\"metaType\":\"EnvironmentVariable\"},{\"metaArea\":\"Inventory\",\"metaFlows\":\"Admin | Sync Template v3 (Portals)\",\"metaName\":\"FullInventory\",\"metaOrder\":7,\"metaSolution\":\"Core\",\"metaType\":\"EnvironmentVariable\"},{\"metaArea\":\"Inventory\",\"metaFlows\":\"Admin | Sync Template v3 (PVA)\",\"metaName\":\"FullInventory\",\"metaOrder\":8,\"metaSolution\":\"Core\",\"metaType\":\"EnvironmentVariable\"},{\"metaArea\":\"Inventory\",\"metaFlows\":\"Admin | Sync Template v3 (Solutions)\",\"metaName\":\"FullInventory\",\"metaOrder\":9,\"metaSolution\":\"Core\",\"metaType\":\"EnvironmentVariable\"},{\"metaArea\":\"Inactivity Notifications\",\"metaFlows\":\"Admin | Inactivity notifications v2 (Start Approval for Flows)\",\"metaName\":\"InactivityNotifications-PastTime-Interval\",\"metaOrder\":1,\"metaSolution\":\"Governance\",\"metaType\":\"EnvironmentVariable\"},{\"metaArea\":\"Inactivity Notifications\",\"metaFlows\":\"Admin | Inactivity notifications v2 (Start Approval for Apps)\",\"metaName\":\"InactivityNotifications-PastTime-Interval\",\"metaOrder\":2,\"metaSolution\":\"Governance\",\"metaType\":\"EnvironmentVariable\"},{\"metaArea\":\"Inactivity Notifications\",\"metaFlows\":\"Admin | Inactivity notifications v2 (Start Approval for Flows)\",\"metaName\":\"InactivityNotifications-PastTime-Unit\",\"metaOrder\":1,\"metaSolution\":\"Governance\",\"metaType\":\"EnvironmentVariable\"},{\"metaArea\":\"Inactivity Notifications\",\"metaFlows\":\"Admin | Inactivity notifications v2 (Start Approval for Apps)\",\"metaName\":\"InactivityNotifications-PastTime-Unit\",\"metaOrder\":2,\"metaSolution\":\"Governance\",\"metaType\":\"EnvironmentVariable\"},{\"metaArea\":\"Inventory\",\"metaFlows\":\"Admin | Inactivity notifications v2 (Start Approval for Apps)\",\"metaName\":\"Individual Admin\",\"metaOrder\":1,\"metaSolution\":\"Core\",\"metaType\":\"EnvironmentVariable\"},{\"metaArea\":\"Inventory\",\"metaFlows\":\"Admin | Inactivity notifications v2 (Start Approval for Flows)\",\"metaName\":\"Individual Admin\",\"metaOrder\":2,\"metaSolution\":\"Core\",\"metaType\":\"EnvironmentVariable\"},{\"metaArea\":\"Inventory\",\"metaFlows\":\"App Catalog \\u003E Request Access\",\"metaName\":\"Individual Admin\",\"metaOrder\":3,\"metaSolution\":\"Core\",\"metaType\":\"EnvironmentVariable\"},{\"metaArea\":\"Inventory\",\"metaFlows\":\"Microsoft Teams Admin |Weekly Clean Up of Microsoft Teams environments\",\"metaName\":\"Individual Admin\",\"metaOrder\":4,\"metaSolution\":\"Core\",\"metaType\":\"EnvironmentVariable\"},{\"metaArea\":\"Inventory\",\"metaFlows\":\"Microsoft Teams Admin | Ask for Business Justification when Microsoft Teams environment is created\",\"metaName\":\"Individual Admin\",\"metaOrder\":5,\"metaSolution\":\"Core\",\"metaType\":\"EnvironmentVariable\"},{\"metaArea\":\"Inventory\",\"metaFlows\":\"Pulse [Child] - Post adaptive cards to maker\",\"metaName\":\"Individual Admin\",\"metaOrder\":6,\"metaSolution\":\"Core\",\"metaType\":\"EnvironmentVariable\"},{\"metaArea\":\"Inventory\",\"metaFlows\":\"Request Orphaned Objects Reassigned (Child)\",\"metaName\":\"Individual Admin\",\"metaOrder\":7,\"metaSolution\":\"Core\",\"metaType\":\"EnvironmentVariable\"},{\"metaArea\":\"Inventory\",\"metaFlows\":\"Request Orphaned Objects Reassigned (Parent)\",\"metaName\":\"Individual Admin\",\"metaOrder\":8,\"metaSolution\":\"Core\",\"metaType\":\"EnvironmentVariable\"},{\"metaArea\":\"Inventory\",\"metaFlows\":\"Admin | Sync Template v3 (Apps)\",\"metaName\":\"InventoryFilter_DaysToLookBack\",\"metaOrder\":1,\"metaSolution\":\"Core\",\"metaType\":\"EnvironmentVariable\"},{\"metaArea\":\"Inventory\",\"metaFlows\":\"Admin | Sync Template v3 (Flows)\",\"metaName\":\"InventoryFilter_DaysToLookBack\",\"metaOrder\":2,\"metaSolution\":\"Core\",\"metaType\":\"EnvironmentVariable\"},{\"metaArea\":\"Inventory\",\"metaFlows\":\"Admin | Sync Template v3\",\"metaName\":\"is Full Tenant Inventory\",\"metaOrder\":1,\"metaSolution\":\"Core\",\"metaType\":\"EnvironmentVariable\"},{\"metaArea\":\"Inventory\",\"metaFlows\":\"Admin | Broken Connection Cleanup\",\"metaName\":\"ProductionEnvironment\",\"metaOrder\":1,\"metaSolution\":\"Core\",\"metaType\":\"EnvironmentVariable\"},{\"metaArea\":\"Inventory\",\"metaFlows\":\"Admin | Compliance detail request v3\",\"metaName\":\"ProductionEnvironment\",\"metaOrder\":2,\"metaSolution\":\"Core\",\"metaType\":\"EnvironmentVariable\"},{\"metaArea\":\"Inventory\",\"metaFlows\":\"Admin | Compliance Details Request eMail (Apps)\",\"metaName\":\"ProductionEnvironment\",\"metaOrder\":3,\"metaSolution\":\"Core\",\"metaType\":\"EnvironmentVariable\"},{\"metaArea\":\"Inventory\",\"metaFlows\":\"Admin | Compliance Details Request eMail (Chatbots)\",\"metaName\":\"ProductionEnvironment\",\"metaOrder\":4,\"metaSolution\":\"Core\",\"metaType\":\"EnvironmentVariable\"},{\"metaArea\":\"Inventory\",\"metaFlows\":\"Admin | Compliance Details Request eMail (Custom Connectors)\",\"metaName\":\"ProductionEnvironment\",\"metaOrder\":5,\"metaSolution\":\"Core\",\"metaType\":\"EnvironmentVariable\"},{\"metaArea\":\"Inventory\",\"metaFlows\":\"Admin | Compliance Details Request eMail (Desktop Flows)\",\"metaName\":\"ProductionEnvironment\",\"metaOrder\":6,\"metaSolution\":\"Core\",\"metaType\":\"EnvironmentVariable\"},{\"metaArea\":\"Inventory\",\"metaFlows\":\"Admin | Compliance Details Request eMail (Flows)\",\"metaName\":\"ProductionEnvironment\",\"metaOrder\":7,\"metaSolution\":\"Core\",\"metaType\":\"EnvironmentVariable\"},{\"metaArea\":\"Inventory\",\"metaFlows\":\"Admin | Email Managers Ignored Inactivity notifications Approvals\",\"metaName\":\"ProductionEnvironment\",\"metaOrder\":8,\"metaSolution\":\"Core\",\"metaType\":\"EnvironmentVariable\"},{\"metaArea\":\"Inventory\",\"metaFlows\":\"Admin | Inactivity notifications v2 (Clean Up and Delete)\",\"metaName\":\"ProductionEnvironment\",\"metaOrder\":9,\"metaSolution\":\"Core\",\"metaType\":\"EnvironmentVariable\"},{\"metaArea\":\"Inventory\",\"metaFlows\":\"Admin | Inactivity notifications v2 (Start Approval for Apps)\",\"metaName\":\"ProductionEnvironment\",\"metaOrder\":10,\"metaSolution\":\"Core\",\"metaType\":\"EnvironmentVariable\"},{\"metaArea\":\"Inventory\",\"metaFlows\":\"Admin | Inactivity notifications v2 (Start Approval for Flows)\",\"metaName\":\"ProductionEnvironment\",\"metaOrder\":11,\"metaSolution\":\"Core\",\"metaType\":\"EnvironmentVariable\"},{\"metaArea\":\"Inventory\",\"metaFlows\":\"Admin | Set app quarantine status\",\"metaName\":\"ProductionEnvironment\",\"metaOrder\":12,\"metaSolution\":\"Core\",\"metaType\":\"EnvironmentVariable\"},{\"metaArea\":\"Inventory\",\"metaFlows\":\"Admin | Welcome Email v3\",\"metaName\":\"ProductionEnvironment\",\"metaOrder\":13,\"metaSolution\":\"Core\",\"metaType\":\"EnvironmentVariable\"},{\"metaArea\":\"Inventory\",\"metaFlows\":\"App Catalog \\u003E Request Access\",\"metaName\":\"ProductionEnvironment\",\"metaOrder\":14,\"metaSolution\":\"Core\",\"metaType\":\"EnvironmentVariable\"},{\"metaArea\":\"Inventory\",\"metaFlows\":\"Env Request | Cleanup environments\",\"metaName\":\"ProductionEnvironment\",\"metaOrder\":15,\"metaSolution\":\"Core\",\"metaType\":\"EnvironmentVariable\"},{\"metaArea\":\"Inventory\",\"metaFlows\":\"Env Request | Create approved environment\",\"metaName\":\"ProductionEnvironment\",\"metaOrder\":16,\"metaSolution\":\"Core\",\"metaType\":\"EnvironmentVariable\"},{\"metaArea\":\"Inventory\",\"metaFlows\":\"Env Request | Notify requestor when rejected\",\"metaName\":\"ProductionEnvironment\",\"metaOrder\":17,\"metaSolution\":\"Core\",\"metaType\":\"EnvironmentVariable\"},{\"metaArea\":\"Inventory\",\"metaFlows\":\"Microsoft Teams Admin | Ask for Business Justification when Microsoft Teams environment is created\",\"metaName\":\"ProductionEnvironment\",\"metaOrder\":18,\"metaSolution\":\"Core\",\"metaType\":\"EnvironmentVariable\"},{\"metaArea\":\"Inventory\",\"metaFlows\":\"Microsoft Teams Admin | Send Reminder Mail\",\"metaName\":\"ProductionEnvironment\",\"metaOrder\":19,\"metaSolution\":\"Core\",\"metaType\":\"EnvironmentVariable\"},{\"metaArea\":\"Inventory\",\"metaFlows\":\"Microsoft Teams Admin |Weekly Clean Up of Microsoft Teams environments\",\"metaName\":\"ProductionEnvironment\",\"metaOrder\":20,\"metaSolution\":\"Core\",\"metaType\":\"EnvironmentVariable\"},{\"metaArea\":\"Inventory\",\"metaFlows\":\"Pulse [Child] - Post adaptive cards to maker\",\"metaName\":\"ProductionEnvironment\",\"metaOrder\":21,\"metaSolution\":\"Core\",\"metaType\":\"EnvironmentVariable\"},{\"metaArea\":\"Inventory\",\"metaFlows\":\"Request Orphaned Objects Reassigned (Child)\",\"metaName\":\"ProductionEnvironment\",\"metaOrder\":22,\"metaSolution\":\"Core\",\"metaType\":\"EnvironmentVariable\"},{\"metaArea\":\"Inventory\",\"metaFlows\":\"Request Orphaned Objects Reassigned (Parent)\",\"metaName\":\"ProductionEnvironment\",\"metaOrder\":23,\"metaSolution\":\"Core\",\"metaType\":\"EnvironmentVariable\"},{\"metaArea\":\"Inventory\",\"metaFlows\":\"Training In A Day | Feedback Reminder\",\"metaName\":\"ProductionEnvironment\",\"metaOrder\":24,\"metaSolution\":\"Core\",\"metaType\":\"EnvironmentVariable\"},{\"metaArea\":\"Inventory\",\"metaFlows\":\"Training In A Day | Registration Confirmation\",\"metaName\":\"ProductionEnvironment\",\"metaOrder\":25,\"metaSolution\":\"Core\",\"metaType\":\"EnvironmentVariable\"},{\"metaArea\":\"Inventory\",\"metaFlows\":\"Training In A Day | Reminder 3 days prior event\",\"metaName\":\"ProductionEnvironment\",\"metaOrder\":26,\"metaSolution\":\"Core\",\"metaType\":\"EnvironmentVariable\"},{\"metaArea\":\"Nurture\",\"metaFlows\":\"Pulse - Survey Makers for CoE feedback\",\"metaName\":\"Pulse - How many makers to survey?\",\"metaOrder\":1,\"metaSolution\":\"Nurture\",\"metaType\":\"EnvironmentVariable\"},{\"metaArea\":\"Quarantine\",\"metaFlows\":\"Admin | Quarantine non-compliant apps\",\"metaName\":\"Quarantine Apps after x days of non-compliance\",\"metaOrder\":1,\"metaSolution\":\"Governance\",\"metaType\":\"EnvironmentVariable\"},{\"metaArea\":\"Audit Logs\",\"metaFlows\":\"Admin | Sync Audit Logs\",\"metaName\":\"StartTime-Interval\",\"metaOrder\":1,\"metaSolution\":\"Audit Logs\",\"metaType\":\"EnvironmentVariable\"},{\"metaArea\":\"Audit Logs\",\"metaFlows\":\"Admin | Sync Audit Logs\",\"metaName\":\"StartTime-Unit\",\"metaOrder\":1,\"metaSolution\":\"Audit Logs\",\"metaType\":\"EnvironmentVariable\"},{\"metaArea\":\"Audit Logs\",\"metaFlows\":\"Admin | Sync Audit Logs\",\"metaName\":\"TimeInterval-Interval\",\"metaOrder\":1,\"metaSolution\":\"Audit Logs\",\"metaType\":\"EnvironmentVariable\"},{\"metaArea\":\"Audit Logs\",\"metaFlows\":\"[Child] Admin | Sync Logs\",\"metaName\":\"TimeInterval-Interval\",\"metaOrder\":1,\"metaSolution\":\"Audit Logs\",\"metaType\":\"EnvironmentVariable\"},{\"metaArea\":\"Audit Logs\",\"metaFlows\":\"[Child] Admin | Sync Logs\",\"metaName\":\"TimeInterval-Unit\",\"metaOrder\":1,\"metaSolution\":\"Audit Logs\",\"metaType\":\"EnvironmentVariable\"},{\"metaArea\":\"Audit Logs\",\"metaFlows\":\"Admin | Sync Audit Logs\",\"metaName\":\"TimeInterval-Unit\",\"metaOrder\":2,\"metaSolution\":\"Audit Logs\",\"metaType\":\"EnvironmentVariable\"},{\"metaArea\":\"Audit Logs\",\"metaFlows\":\"Admin | Sync Audit Logs\",\"metaName\":\"TimeSegments-CountLimit\",\"metaOrder\":2,\"metaSolution\":\"Audit Logs\",\"metaType\":\"EnvironmentVariable\"},{\"metaArea\":\"Nurture\",\"metaFlows\":\"Admin | Welcome Email v3\",\"metaName\":\"Community URL\",\"metaOrder\":1,\"metaSolution\":\"Core\",\"metaType\":\"EnvironmentVariable\"},{\"metaArea\":\"Nurture\",\"metaFlows\":\"Training In A Day | Registration Confirmation\",\"metaName\":\"Community URL\",\"metaOrder\":2,\"metaSolution\":\"Core\",\"metaType\":\"EnvironmentVariable\"},{\"metaArea\":\"Nurture\",\"metaFlows\":\"Training In A Day | Reminder 3 days prior event\",\"metaName\":\"Community URL\",\"metaOrder\":3,\"metaSolution\":\"Core\",\"metaType\":\"EnvironmentVariable\"},{\"metaArea\":\"Inactivity Processes\",\"metaFlows\":\"Admin | Broken Connection Cleanup\",\"metaName\":\"Delete Broken Connections Age (Days)\",\"metaOrder\":1,\"metaSolution\":\"Governance\",\"metaType\":\"EnvironmentVariable\"},{\"metaArea\":\"Inventory\",\"metaFlows\":\"HELPER - Maker Check\",\"metaName\":\"Disabled Users are Orphaned\",\"metaOrder\":1,\"metaSolution\":\"Core\",\"metaType\":\"EnvironmentVariable\"}]",
    "IsSampleData": false,
    "IsWritable": false,
    "Name": "EnvVarMetadata",
    "OrderedColumnNames": [
      "metaName",
      "metaSolution",
      "metaArea",
      "metaFlows",
      "metaOrder",
      "metaType"
    ],
    "OriginalName": "EnvVarMetadata",
    "OriginalSchema": "*[metaArea:s, metaFlows:s, metaName:s, metaOrder:n, metaSolution:s, metaType:s]",
    "Schema": "*[metaArea:s, metaFlows:s, metaName:s, metaOrder:n, metaSolution:s, metaType:s]",
    "Token": "dummyToken",
    "Type": "StaticDataSourceInfo"
  }
]