[
  {
    "CdsFCBContext": "{\"FileType\":true,\"ImageExternalStorage\":true}",
    "EntitySetName": "transactioncurrencies",
    "IsHidden": false,
    "IsSampleData": false,
    "IsWritable": true,
    "LogicalName": "transactioncurrency",
    "Name": "Currencies",
    "NativeCDSDataSourceInfoNameMapping": {
      "adx_inviteredemption_transactioncurrency_transactioncurrencyid": "Invite Redemptions",
      "adx_portalcomment_transactioncurrency_transactioncurrencyid": "Portal Comments",
      "basecurrency_organization": "Organizations",
      "chat_transactioncurrency_transactioncurrencyid": "Teams chats",
      "createdby": "Created By",
      "createdon": "Created On",
      "createdonbehalfby": "Created By (Delegate)",
      "currencyname": "Currency Name",
      "currencyprecision": "Currency Precision",
      "currencysymbol": "Currency Symbol",
      "entityimage": "Entity Image",
      "entityimageid": "Entity Image Id",
      "exchangerate": "Exchange Rate",
      "importsequencenumber": "Import Sequence Number",
      "isocurrencycode": "Currency Code",
      "modifiedby": "Modified By",
      "modifiedon": "Modified On",
      "modifiedonbehalfby": "Modified By (Delegate)",
      "msfp_alert_transactioncurrency_transactioncurrencyid": "Customer Voice alert",
      "msfp_surveyinvite_transactioncurrency_transactioncurrencyid": "Customer Voice survey invites",
      "msfp_surveyresponse_transactioncurrency_transactioncurrencyid": "Customer Voice survey responses",
      "organizationid": "Organization",
      "overriddencreatedon": "Record Created On",
      "statecode": "Status",
      "statuscode": "Status Reason",
      "transactioncurrency_account": "Accounts",
      "transactioncurrency_actioncard": "Action Cards",
      "TransactionCurrency_ActionCardUserState": "ActionCardUserStates",
      "TransactionCurrency_ActivityPointer": "Activities",
      "TransactionCurrency_Appointment": "Appointments",
      "TransactionCurrency_AsyncOperations": "System Jobs",
      "TransactionCurrency_BusinessUnit": "Business Units",
      "TransactionCurrency_Connection": "Connections",
      "transactioncurrency_contact": "Contacts",
      "TransactionCurrency_cr5cd_Averagecosts": "Average costs",
      "TransactionCurrency_cr9cd_teamexpenses": "Team Expenses",
      "TransactionCurrency_CustomerAddress": "Addresses",
      "TransactionCurrency_DuplicateBaseRecord": "Duplicate Records (TransactionCurrency_DuplicateBaseRecord)",
      "TransactionCurrency_DuplicateMatchingRecord": "Duplicate Records (TransactionCurrency_DuplicateMatchingRecord)",
      "TransactionCurrency_Email": "Email Messages",
      "transactioncurrency_expiredprocess": "Expired Process",
      "TransactionCurrency_Fax": "Faxes",
      "transactioncurrency_feedback": "Feedback",
      "TransactionCurrency_InteractionForEmail": "Interactions for Email",
      "TransactionCurrency_Letter": "Letters",
      "TransactionCurrency_MailMergeTemplate": "Mail Merge Templates",
      "transactioncurrency_newprocess": "New Process",
      "TransactionCurrency_officegraphdocument": "Office Graph Documents",
      "TransactionCurrency_PhoneCall": "Phone Calls",
      "transactioncurrency_position": "Positions",
      "TransactionCurrency_ProcessSessions": "Process Sessions",
      "TransactionCurrency_Queue": "Queues",
      "TransactionCurrency_QueueItem": "Queue Items",
      "TransactionCurrency_recommendeddocument": "Document Suggestions",
      "TransactionCurrency_RecurringAppointmentMaster": "Recurring Appointments",
      "TransactionCurrency_ReportCategory": "Report Related Categories",
      "TransactionCurrency_SharePointDocumentLocation": "Document Locations",
      "TransactionCurrency_SharePointSite": "SharePoint Sites",
      "TransactionCurrency_SyncErrors": "Sync Errors",
      "TransactionCurrency_SystemUser": "Users",
      "TransactionCurrency_Task": "Tasks",
      "TransactionCurrency_Team": "Teams",
      "TransactionCurrency_Theme": "Themes",
      "transactioncurrency_translationprocess": "Translation Process",
      "transactioncurrency_usersettings": "User Settings",
      "transactioncurrencyid": "Transaction Currency",
      "versionnumber": "Version Number"
    },
    "PreferredName": "Currencies",
    "Type": "NativeCDSDataSourceInfo"
  },
  {
    "DisplayName": "Currencies (Views)",
    "Name": "_transactioncurrency_views",
    "RelatedEntityName": "Currencies",
    "TrimmedViewName": true,
    "Type": "ViewInfo",
    "ViewInfoNameMapping": {
      "03b869f9-5c8e-43ba-be3f-43ed965de59d": "Currency Advanced Find View",
      "a2420357-be1d-4480-8da8-0ee8c33cd95a": "Inactive Currencies",
      "be87bffc-5a00-4b77-8979-14b8db8fa310": "All Currencies Associated View",
      "c8f16d88-e49c-48dd-af54-a6bd5102c439": "Active Currencies",
      "cd5625b0-dda8-4ee2-b13f-b9331e027c8a": "Currency Lookup View",
      "e70701bd-134e-41a7-be66-67d8dd30d0e3": "All Currencies"
    }
  },
  {
    "DisplayName": "Status (Currencies)",
    "Name": "transactioncurrency_statecode",
    "OptionSetInfoNameMapping": {
      "0": "Active",
      "1": "Inactive"
    },
    "OptionSetIsBooleanValued": false,
    "OptionSetIsGlobal": false,
    "OptionSetReference": {
      "OptionSetReferenceItem0": {
        "OptionSetReferenceColumnName": "statecode",
        "OptionSetReferenceEntityName": "Currencies"
      }
    },
    "OptionSetTypeKey": "StateType",
    "RelatedColumnInvariantName": "statecode",
    "RelatedEntityName": "Currencies",
    "Type": "OptionSetInfo"
  },
  {
    "DisplayName": "Status Reason (Currencies)",
    "Name": "transactioncurrency_statuscode",
    "OptionSetInfoNameMapping": {
      "1": "Active",
      "2": "Inactive"
    },
    "OptionSetIsBooleanValued": false,
    "OptionSetIsGlobal": false,
    "OptionSetReference": {
      "OptionSetReferenceItem0": {
        "OptionSetReferenceColumnName": "statuscode",
        "OptionSetReferenceEntityName": "Currencies"
      }
    },
    "OptionSetTypeKey": "StatusType",
    "RelatedColumnInvariantName": "statuscode",
    "RelatedEntityName": "Currencies",
    "Type": "OptionSetInfo"
  }
]