<?xml version="1.0" encoding="utf-8"?>
<PluginAssembly FullName="alm.plugins, Version=1.0.0.0, Culture=neutral, PublicKeyToken=d48975769547e200" PluginAssemblyId="73491cdd-8719-4e90-9690-1ccec68f61d7" CustomizationLevel="1" xmlns:xsi="http://www.w3.org/2001/XMLSchema-instance">
  <IsolationMode>2</IsolationMode>
  <SourceType>0</SourceType>
  <IntroducedVersion>1.0</IntroducedVersion>
  <FileName>/PluginAssemblies/almplugins-73491CDD-8719-4E90-9690-1CCEC68F61D7/almplugins.dll</FileName>
  <PluginTypes>
    <PluginType AssemblyQualifiedName="alm.plugins.PreAlmAcceleratorSampleCreate, alm.plugins, Version=1.0.0.0, Culture=neutral, PublicKeyToken=d48975769547e200" PluginTypeId="87d2f9ac-9c3c-4470-9dcb-d8d6bb720e1c" Name="alm.plugins.PreAlmAcceleratorSampleCreate">
      <FriendlyName>9963e1ff-3d52-4dd2-904c-7a529250f7c2</FriendlyName>
    </PluginType>
  </PluginTypes>
</PluginAssembly>