<environmentvariabledefinition schemaname="admin_InnovationBacklogAppURL">
  <defaultvalue>https://apps.powerapps.com/play/289cd56e-0998-42ca-9488-325aae7c2d1c</defaultvalue>
  <description default="the url of the main app for the innovation backlog. ready by that app in order to generate urls for email links">
    <label description="the url of the main app for the innovation backlog. ready by that app in order to generate urls for email links" languagecode="1033" />
  </description>
  <displayname default="InnovationBacklogAppURL">
    <label description="InnovationBacklogAppURL" languagecode="1033" />
  </displayname>
  <introducedversion>1.8</introducedversion>
  <iscustomizable>1</iscustomizable>
  <isrequired>0</isrequired>
  <type>100000000</type>
</environmentvariabledefinition>