{
  "7a4857fc-a229-4537-b586-1215a97f6804": {
    "connectionParameters": {
      "sku": "Enterprise"
    },
    "connectionRef": {
      "apiTier": "Standard",
      "displayName": "Office 365 Users",
      "iconUri": "https://connectoricons-prod.azureedge.net/releases/v1.0.1573/1.0.1573.2770/office365users/icon.png",
      "id": "/providers/microsoft.powerapps/apis/shared_office365users",
      "parameterHints": {},
      "parameterHintsV2": {}
    },
    "datasets": {},
    "dataSources": [
      "Office365Users"
    ],
    "dependencies": {},
    "dependents": [],
    "id": "7a4857fc-a229-4537-b586-1215a97f6804"
  },
  "eeaee5c4-ba94-4b76-9297-e48ebee75b31": {
    "connectionParameters": {
      "sku": "Enterprise"
    },
    "connectionRef": {
      "apiTier": "Standard",
      "displayName": "Office 365 Outlook",
      "iconUri": "https://connectoricons-prod.azureedge.net/releases/v1.0.1580/1.0.1580.2838/office365/icon.png",
      "id": "/providers/microsoft.powerapps/apis/shared_office365",
      "parameterHints": {},
      "parameterHintsV2": {}
    },
    "datasets": {},
    "dataSources": [
      "Office365Outlook"
    ],
    "dependencies": {},
    "dependents": [],
    "id": "eeaee5c4-ba94-4b76-9297-e48ebee75b31"
  }
}