<?xml version="1.0" encoding="utf-8"?>
<CanvasApp xmlns:xsi="http://www.w3.org/2001/XMLSchema-instance">
  <Name>coe_environmentcreationrequest_bbe9d</Name>
  <AppVersion>2022-08-01T18:24:27Z</AppVersion>
  <Status>Ready</Status>
  <CreatedByClientVersion>3.22072.25.0</CreatedByClientVersion>
  <MinClientVersion>3.22072.25.0</MinClientVersion>
  <Tags>{"primaryDeviceWidth":"2132","primaryDeviceHeight":"1107","sienaVersion":"20220611T033939Z-3.22054.15.0","deviceCapabilities":"","supportsPortrait":"false","supportsLandscape":"true","primaryFormFactor":"Tablet","publisherVersion":"3.22072.25","minimumRequiredApiVersion":"2.2.0","hasComponent":"true","hasUnlockedComponent":"true","isUnifiedRootApp":"false"}</Tags>
  <IsCdsUpgraded>0</IsCdsUpgraded>
  <GalleryItemId xsi:nil="true"></GalleryItemId>
  <BackgroundColor>rgba(255, 255, 255, 1)</BackgroundColor>
  <DisplayName>Maker - Environment Request</DisplayName>
  <Description>Allows Makers (aka Power Platform developers that are not admins) to request Power Platform Admin services and resources like new Environments and applying DLP Policy changes.</Description>
  <CommitMessage>add guid string on new record creation</CommitMessage>
  <Publisher></Publisher>
  <AuthorizationReferences>[]</AuthorizationReferences>
  <ConnectionReferences>{"d91cb925-97f3-4b2a-aacc-27d0450c0893":{"id":"/providers/microsoft.powerapps/apis/shared_office365users","displayName":"Office 365 Users","iconUri":"https://connectoricons-prod.azureedge.net/releases/v1.0.1587/1.0.1587.2924/office365users/icon.png","dataSources":["Office365Users"],"dependencies":[],"dependents":[],"parameterHints":{},"parameterHintsV2":{},"isOnPremiseConnection":false,"bypassConsent":false,"dataSets":{},"apiTier":"Standard","actions":["MyProfileV2","SearchUserV2","UserPhotoMetadata","UserPhotoV2"]},"a4b47abc-264d-4248-a7e0-4ec5c4c04094":{"id":"/providers/microsoft.powerapps/apis/shared_powerplatformforadmins","displayName":"Power Platform for Admins","iconUri":"https://connectoricons-prod.azureedge.net/releases/v1.0.1570/1.0.1570.2764/powerplatformforadmins/icon.png","dataSources":["PowerPlatformforAdmins"],"dependencies":[],"dependents":[],"parameterHints":{},"parameterHintsV2":{},"isOnPremiseConnection":false,"bypassConsent":false,"dataSets":{},"apiTier":"Standard","actions":["ListSupportedLocations","ListEnvironmentCurrencies","ListEnvironmentLanguages","RemoveAdminEnvironment","GetAdminEnvironment","ListPoliciesV2"]},"1e06a715-6861-4459-9379-6b5c7f27841f":{"id":"/providers/microsoft.powerapps/apis/shared_powerappsforappmakers","displayName":"Power Apps for Makers","iconUri":"https://connectoricons-prod.azureedge.net/releases/v1.0.1551/1.0.1551.2693/powerappsforappmakers/icon.png","dataSources":["PowerAppsforMakers"],"dependencies":[],"dependents":[],"parameterHints":{},"parameterHintsV2":{},"isOnPremiseConnection":false,"bypassConsent":false,"dataSets":{},"apiTier":"Standard","actions":["GetEnvironments","GetConnectors"]},"81b10fbc-1216-47e5-860e-e2c93d28cd01":{"id":"/providers/microsoft.powerapps/apis/shared_office365groups","displayName":"Office 365 Groups","iconUri":"https://connectoricons-prod.azureedge.net/releases/v1.0.1588/1.0.1588.2938/office365groups/icon.png","dataSources":["Office365Groups"],"dependencies":[],"dependents":[],"parameterHints":{},"parameterHintsV2":{},"isOnPremiseConnection":false,"bypassConsent":false,"dataSets":{},"apiTier":"Standard","actions":["ListOwnedGroupsV3"]}}</ConnectionReferences>
  <DatabaseReferences>{"default.cds":{"databaseDetails":{"referenceType":"Environmental","environmentName":"default.cds","overrideValues":{"status":"NotSpecified"}},"dataSources":{"Environment Creation Requests":{"entitySetName":"coe_environmentcreationrequests","logicalName":"coe_environmentcreationrequest"},"Makers":{"entitySetName":"admin_makers","logicalName":"admin_maker"},"Users":{"entitySetName":"systemusers","logicalName":"systemuser"},"PowerApps Connectors":{"entitySetName":"admin_connectors","logicalName":"admin_connector"},"Security Roles":{"entitySetName":"roles","logicalName":"role"},"Teams":{"entitySetName":"teams","logicalName":"team"},"Environment Variable Values":{"entitySetName":"environmentvariablevalues","logicalName":"environmentvariablevalue"},"Environment Variable Definitions":{"entitySetName":"environmentvariabledefinitions","logicalName":"environmentvariabledefinition"},"Environments":{"entitySetName":"admin_environments","logicalName":"admin_environment"},"DLP Policy Change Requests":{"entitySetName":"coe_dlppolicychangerequests","logicalName":"coe_dlppolicychangerequest"},"DLP Policies":{"entitySetName":"admin_dlppolicies","logicalName":"admin_dlppolicy"},"Environment Business Areas":{"entitySetName":"admin_environmentbusinessareas","logicalName":"admin_environmentbusinessarea"}}}}</DatabaseReferences>
  <AppComponents>[]</AppComponents>
  <AppComponentDependencies>[]</AppComponentDependencies>
  <CanvasAppType>0</CanvasAppType>
  <BypassConsent>0</BypassConsent>
  <AdminControlBypassConsent>0</AdminControlBypassConsent>
  <EmbeddedApp xsi:nil="true"></EmbeddedApp>
  <IntroducedVersion>1.0</IntroducedVersion>
  <CdsDependencies>{"cdsdependencies":[{"logicalname":"coe_environmentcreationrequest","componenttype":1},{"logicalname":"admin_maker","componenttype":1},{"logicalname":"systemuser","componenttype":1},{"logicalname":"admin_connector","componenttype":1},{"logicalname":"role","componenttype":1},{"logicalname":"team","componenttype":1},{"logicalname":"environmentvariablevalue","componenttype":1},{"logicalname":"environmentvariabledefinition","componenttype":1},{"logicalname":"admin_environment","componenttype":1},{"logicalname":"coe_dlppolicychangerequest","componenttype":1},{"logicalname":"admin_dlppolicy","componenttype":1},{"logicalname":"admin_environmentbusinessarea","componenttype":1}]}</CdsDependencies>
  <IsCustomizable>1</IsCustomizable>
  <BackgroundImageUri>/CanvasApps/coe_environmentcreationrequest_bbe9d_BackgroundImageUri</BackgroundImageUri>
  <DocumentUri>/CanvasApps/coe_environmentcreationrequest_bbe9d_DocumentUri.msapp</DocumentUri>
</CanvasApp>