{
  "ControlStates": {
    "envvar_area": {
      "AllowAccessToGlobals": true,
      "ControlPropertyState": [
        "Live",
        "Overflow",
        {
          "AFDDataSourceName": "",
          "AutoRuleBindingEnabled": false,
          "AutoRuleBindingString": "ThisItem.metaFlagged",
          "InvariantPropertyName": "Text",
          "IsLockable": false,
          "NameMapSourceSchema": "?"
        },
        "Role",
        "Color",
        "DisabledColor",
        "PressedColor",
        "HoverColor",
        "BorderColor",
        "DisabledBorderColor",
        "PressedBorderColor",
        "HoverBorderColor",
        "BorderStyle",
        "FocusedBorderColor",
        "Fill",
        "DisabledFill",
        "PressedFill",
        "HoverFill",
        "Font",
        "FontWeight",
        "Align",
        "VerticalAlign",
        {
          "AFDDataSourceName": "",
          "AutoRuleBindingEnabled": false,
          "AutoRuleBindingString": "354",
          "InvariantPropertyName": "X",
          "IsLockable": false,
          "NameMapSourceSchema": "?"
        },
        {
          "AFDDataSourceName": "",
          "AutoRuleBindingEnabled": false,
          "AutoRuleBindingString": "1",
          "InvariantPropertyName": "Y",
          "IsLockable": false,
          "NameMapSourceSchema": "?"
        },
        {
          "AFDDataSourceName": "",
          "AutoRuleBindingEnabled": false,
          "AutoRuleBindingString": "148",
          "InvariantPropertyName": "Width",
          "IsLockable": false,
          "NameMapSourceSchema": "?"
        },
        "Height",
        "DisplayMode",
        "OnSelect",
        "ZIndex",
        "LineHeight",
        "BorderThickness",
        "FocusedBorderThickness",
        "Size",
        "Italic",
        "Underline",
        "Strikethrough",
        "PaddingTop",
        "PaddingRight",
        "PaddingBottom",
        "PaddingLeft"
      ],
      "HasDynamicProperties": false,
      "IsAutoGenerated": false,
      "IsComponentDefinition": false,
      "IsDataControl": false,
      "IsFromScreenLayout": false,
      "IsGroupControl": false,
      "IsLocked": false,
      "LayoutName": "",
      "MetaDataIDKey": "",
      "Name": "envvar_area",
      "ParentIndex": 2,
      "PersistMetaDataIDKey": false,
      "Properties": [
        {
          "Category": "Data",
          "PropertyName": "Role",
          "RuleProviderType": "Unknown"
        },
        {
          "Category": "Data",
          "PropertyName": "Text",
          "RuleProviderType": "Unknown"
        },
        {
          "Category": "Data",
          "PropertyName": "Live",
          "RuleProviderType": "Unknown"
        },
        {
          "Category": "Design",
          "PropertyName": "FocusedBorderThickness",
          "RuleProviderType": "Unknown"
        },
        {
          "Category": "Design",
          "PropertyName": "PaddingLeft",
          "RuleProviderType": "Unknown"
        },
        {
          "Category": "Design",
          "PropertyName": "PressedColor",
          "RuleProviderType": "Unknown"
        },
        {
          "Category": "Design",
          "PropertyName": "Color",
          "RuleProviderType": "Unknown"
        },
        {
          "Category": "Design",
          "PropertyName": "Overflow",
          "RuleProviderType": "Unknown"
        },
        {
          "Category": "Design",
          "PropertyName": "PaddingRight",
          "RuleProviderType": "Unknown"
        },
        {
          "Category": "Design",
          "PropertyName": "DisabledColor",
          "RuleProviderType": "Unknown"
        },
        {
          "Category": "Design",
          "PropertyName": "HoverFill",
          "RuleProviderType": "Unknown"
        },
        {
          "Category": "Design",
          "PropertyName": "BorderColor",
          "RuleProviderType": "Unknown"
        },
        {
          "Category": "Design",
          "PropertyName": "DisabledBorderColor",
          "RuleProviderType": "Unknown"
        },
        {
          "Category": "Design",
          "PropertyName": "PressedFill",
          "RuleProviderType": "Unknown"
        },
        {
          "Category": "Design",
          "PropertyName": "FocusedBorderColor",
          "RuleProviderType": "Unknown"
        },
        {
          "Category": "Design",
          "PropertyName": "DisabledFill",
          "RuleProviderType": "Unknown"
        },
        {
          "Category": "Design",
          "PropertyName": "HoverBorderColor",
          "RuleProviderType": "Unknown"
        },
        {
          "Category": "Design",
          "PropertyName": "Fill",
          "RuleProviderType": "Unknown"
        },
        {
          "Category": "Design",
          "PropertyName": "BorderStyle",
          "RuleProviderType": "Unknown"
        },
        {
          "Category": "Design",
          "PropertyName": "PressedBorderColor",
          "RuleProviderType": "Unknown"
        },
        {
          "Category": "Design",
          "PropertyName": "HoverColor",
          "RuleProviderType": "Unknown"
        },
        {
          "Category": "Design",
          "PropertyName": "Font",
          "RuleProviderType": "Unknown"
        },
        {
          "Category": "Design",
          "PropertyName": "FontWeight",
          "RuleProviderType": "Unknown"
        },
        {
          "Category": "Design",
          "PropertyName": "Align",
          "RuleProviderType": "Unknown"
        },
        {
          "Category": "Design",
          "PropertyName": "VerticalAlign",
          "RuleProviderType": "Unknown"
        },
        {
          "Category": "Design",
          "PropertyName": "X",
          "RuleProviderType": "Unknown"
        },
        {
          "Category": "Design",
          "PropertyName": "Y",
          "RuleProviderType": "Unknown"
        },
        {
          "Category": "Design",
          "PropertyName": "Width",
          "RuleProviderType": "Unknown"
        },
        {
          "Category": "Design",
          "PropertyName": "Height",
          "RuleProviderType": "Unknown"
        },
        {
          "Category": "Design",
          "PropertyName": "DisplayMode",
          "RuleProviderType": "Unknown"
        },
        {
          "Category": "Design",
          "PropertyName": "Size",
          "RuleProviderType": "Unknown"
        },
        {
          "Category": "Design",
          "PropertyName": "ZIndex",
          "RuleProviderType": "Unknown"
        },
        {
          "Category": "Design",
          "PropertyName": "PaddingTop",
          "RuleProviderType": "Unknown"
        },
        {
          "Category": "Design",
          "PropertyName": "LineHeight",
          "RuleProviderType": "Unknown"
        },
        {
          "Category": "Design",
          "PropertyName": "Strikethrough",
          "RuleProviderType": "Unknown"
        },
        {
          "Category": "Design",
          "PropertyName": "Underline",
          "RuleProviderType": "Unknown"
        },
        {
          "Category": "Design",
          "PropertyName": "Italic",
          "RuleProviderType": "Unknown"
        },
        {
          "Category": "Design",
          "PropertyName": "PaddingBottom",
          "RuleProviderType": "Unknown"
        },
        {
          "Category": "Design",
          "PropertyName": "BorderThickness",
          "RuleProviderType": "Unknown"
        },
        {
          "Category": "Behavior",
          "PropertyName": "OnSelect",
          "RuleProviderType": "Unknown"
        }
      ],
      "StyleName": "defaultLabelStyle",
      "Type": "ControlInfo"
    },
    "envvar_area_lbl": {
      "AllowAccessToGlobals": true,
      "ControlPropertyState": [
        "Live",
        "Overflow",
        {
          "AFDDataSourceName": "",
          "AutoRuleBindingEnabled": false,
          "AutoRuleBindingString": "\"Text\"",
          "InvariantPropertyName": "Text",
          "IsLockable": false,
          "NameMapSourceSchema": "?"
        },
        "Role",
        {
          "AFDDataSourceName": "",
          "AutoRuleBindingEnabled": false,
          "AutoRuleBindingString": "RGBA(51, 51, 51, 1)",
          "InvariantPropertyName": "Color",
          "IsLockable": false,
          "NameMapSourceSchema": "?"
        },
        "DisabledColor",
        "PressedColor",
        "HoverColor",
        "BorderColor",
        "DisabledBorderColor",
        "PressedBorderColor",
        "HoverBorderColor",
        "BorderStyle",
        "FocusedBorderColor",
        {
          "AFDDataSourceName": "",
          "AutoRuleBindingEnabled": false,
          "AutoRuleBindingString": "RGBA(0, 0, 0, 0)",
          "InvariantPropertyName": "Fill",
          "IsLockable": false,
          "NameMapSourceSchema": "?"
        },
        "DisabledFill",
        "PressedFill",
        "HoverFill",
        "Font",
        {
          "AFDDataSourceName": "",
          "AutoRuleBindingEnabled": false,
          "AutoRuleBindingString": "",
          "InvariantPropertyName": "FontWeight",
          "IsLockable": false,
          "NameMapSourceSchema": "?"
        },
        "Align",
        "VerticalAlign",
        {
          "AFDDataSourceName": "",
          "AutoRuleBindingEnabled": false,
          "AutoRuleBindingString": "60",
          "InvariantPropertyName": "X",
          "IsLockable": false,
          "NameMapSourceSchema": "?"
        },
        {
          "AFDDataSourceName": "",
          "AutoRuleBindingEnabled": false,
          "AutoRuleBindingString": "60",
          "InvariantPropertyName": "Y",
          "IsLockable": false,
          "NameMapSourceSchema": "?"
        },
        {
          "AFDDataSourceName": "",
          "AutoRuleBindingEnabled": false,
          "AutoRuleBindingString": "150",
          "InvariantPropertyName": "Width",
          "IsLockable": false,
          "NameMapSourceSchema": "?"
        },
        "Height",
        "DisplayMode",
        "ZIndex",
        "LineHeight",
        "BorderThickness",
        "FocusedBorderThickness",
        "Size",
        "Italic",
        "Underline",
        "Strikethrough",
        "PaddingTop",
        "PaddingRight",
        "PaddingBottom",
        "PaddingLeft"
      ],
      "HasDynamicProperties": false,
      "IsAutoGenerated": false,
      "IsComponentDefinition": false,
      "IsDataControl": false,
      "IsFromScreenLayout": false,
      "IsGroupControl": false,
      "IsLocked": false,
      "LayoutName": "",
      "MetaDataIDKey": "",
      "Name": "envvar_area_lbl",
      "ParentIndex": 1,
      "PersistMetaDataIDKey": false,
      "Properties": [
        {
          "Category": "Data",
          "PropertyName": "Text",
          "RuleProviderType": "Unknown"
        },
        {
          "Category": "Data",
          "PropertyName": "Live",
          "RuleProviderType": "Unknown"
        },
        {
          "Category": "Data",
          "PropertyName": "Role",
          "RuleProviderType": "Unknown"
        },
        {
          "Category": "Design",
          "PropertyName": "ZIndex",
          "RuleProviderType": "Unknown"
        },
        {
          "Category": "Design",
          "PropertyName": "Size",
          "RuleProviderType": "Unknown"
        },
        {
          "Category": "Design",
          "PropertyName": "LineHeight",
          "RuleProviderType": "Unknown"
        },
        {
          "Category": "Design",
          "PropertyName": "Overflow",
          "RuleProviderType": "Unknown"
        },
        {
          "Category": "Design",
          "PropertyName": "X",
          "RuleProviderType": "Unknown"
        },
        {
          "Category": "Design",
          "PropertyName": "Color",
          "RuleProviderType": "Unknown"
        },
        {
          "Category": "Design",
          "PropertyName": "PressedFill",
          "RuleProviderType": "Unknown"
        },
        {
          "Category": "Design",
          "PropertyName": "HoverFill",
          "RuleProviderType": "Unknown"
        },
        {
          "Category": "Design",
          "PropertyName": "DisabledColor",
          "RuleProviderType": "Unknown"
        },
        {
          "Category": "Design",
          "PropertyName": "BorderColor",
          "RuleProviderType": "Unknown"
        },
        {
          "Category": "Design",
          "PropertyName": "PressedBorderColor",
          "RuleProviderType": "Unknown"
        },
        {
          "Category": "Design",
          "PropertyName": "HoverBorderColor",
          "RuleProviderType": "Unknown"
        },
        {
          "Category": "Design",
          "PropertyName": "DisabledBorderColor",
          "RuleProviderType": "Unknown"
        },
        {
          "Category": "Design",
          "PropertyName": "FocusedBorderColor",
          "RuleProviderType": "Unknown"
        },
        {
          "Category": "Design",
          "PropertyName": "FocusedBorderThickness",
          "RuleProviderType": "Unknown"
        },
        {
          "Category": "Design",
          "PropertyName": "BorderStyle",
          "RuleProviderType": "Unknown"
        },
        {
          "Category": "Design",
          "PropertyName": "PressedColor",
          "RuleProviderType": "Unknown"
        },
        {
          "Category": "Design",
          "PropertyName": "HoverColor",
          "RuleProviderType": "Unknown"
        },
        {
          "Category": "Design",
          "PropertyName": "Fill",
          "RuleProviderType": "Unknown"
        },
        {
          "Category": "Design",
          "PropertyName": "DisabledFill",
          "RuleProviderType": "Unknown"
        },
        {
          "Category": "Design",
          "PropertyName": "Font",
          "RuleProviderType": "Unknown"
        },
        {
          "Category": "Design",
          "PropertyName": "FontWeight",
          "RuleProviderType": "Unknown"
        },
        {
          "Category": "Design",
          "PropertyName": "Align",
          "RuleProviderType": "Unknown"
        },
        {
          "Category": "Design",
          "PropertyName": "VerticalAlign",
          "RuleProviderType": "Unknown"
        },
        {
          "Category": "Design",
          "PropertyName": "Y",
          "RuleProviderType": "Unknown"
        },
        {
          "Category": "Design",
          "PropertyName": "Width",
          "RuleProviderType": "Unknown"
        },
        {
          "Category": "Design",
          "PropertyName": "Height",
          "RuleProviderType": "Unknown"
        },
        {
          "Category": "Design",
          "PropertyName": "DisplayMode",
          "RuleProviderType": "Unknown"
        },
        {
          "Category": "Design",
          "PropertyName": "BorderThickness",
          "RuleProviderType": "Unknown"
        },
        {
          "Category": "Design",
          "PropertyName": "PaddingBottom",
          "RuleProviderType": "Unknown"
        },
        {
          "Category": "Design",
          "PropertyName": "PaddingLeft",
          "RuleProviderType": "Unknown"
        },
        {
          "Category": "Design",
          "PropertyName": "Strikethrough",
          "RuleProviderType": "Unknown"
        },
        {
          "Category": "Design",
          "PropertyName": "PaddingTop",
          "RuleProviderType": "Unknown"
        },
        {
          "Category": "Design",
          "PropertyName": "PaddingRight",
          "RuleProviderType": "Unknown"
        },
        {
          "Category": "Design",
          "PropertyName": "Italic",
          "RuleProviderType": "Unknown"
        },
        {
          "Category": "Design",
          "PropertyName": "Underline",
          "RuleProviderType": "Unknown"
        }
      ],
      "StyleName": "defaultLabelStyle",
      "Type": "ControlInfo"
    },
    "envvar_flow": {
      "AllowAccessToGlobals": true,
      "ControlPropertyState": [
        "Live",
        "Overflow",
        {
          "AFDDataSourceName": "",
          "AutoRuleBindingEnabled": false,
          "AutoRuleBindingString": "ThisItem.metaSolution",
          "InvariantPropertyName": "Text",
          "IsLockable": false,
          "NameMapSourceSchema": "?"
        },
        "Role",
        "Color",
        "DisabledColor",
        "PressedColor",
        "HoverColor",
        "BorderColor",
        "DisabledBorderColor",
        "PressedBorderColor",
        "HoverBorderColor",
        "BorderStyle",
        "FocusedBorderColor",
        "Fill",
        "DisabledFill",
        "PressedFill",
        "HoverFill",
        "Font",
        "FontWeight",
        "Align",
        "VerticalAlign",
        {
          "AFDDataSourceName": "",
          "AutoRuleBindingEnabled": false,
          "AutoRuleBindingString": "707",
          "InvariantPropertyName": "X",
          "IsLockable": false,
          "NameMapSourceSchema": "?"
        },
        {
          "AFDDataSourceName": "",
          "AutoRuleBindingEnabled": false,
          "AutoRuleBindingString": "1",
          "InvariantPropertyName": "Y",
          "IsLockable": false,
          "NameMapSourceSchema": "?"
        },
        {
          "AFDDataSourceName": "",
          "AutoRuleBindingEnabled": false,
          "AutoRuleBindingString": "150",
          "InvariantPropertyName": "Width",
          "IsLockable": false,
          "NameMapSourceSchema": "?"
        },
        "Height",
        "DisplayMode",
        "OnSelect",
        "ZIndex",
        "LineHeight",
        "BorderThickness",
        "FocusedBorderThickness",
        "Size",
        "Italic",
        "Underline",
        "Strikethrough",
        "PaddingTop",
        "PaddingRight",
        "PaddingBottom",
        "PaddingLeft"
      ],
      "HasDynamicProperties": false,
      "IsAutoGenerated": false,
      "IsComponentDefinition": false,
      "IsDataControl": false,
      "IsFromScreenLayout": false,
      "IsGroupControl": false,
      "IsLocked": false,
      "LayoutName": "",
      "MetaDataIDKey": "",
      "Name": "envvar_flow",
      "ParentIndex": 3,
      "PersistMetaDataIDKey": false,
      "Properties": [
        {
          "Category": "Data",
          "PropertyName": "Role",
          "RuleProviderType": "Unknown"
        },
        {
          "Category": "Data",
          "PropertyName": "Live",
          "RuleProviderType": "Unknown"
        },
        {
          "Category": "Data",
          "PropertyName": "Text",
          "RuleProviderType": "Unknown"
        },
        {
          "Category": "Design",
          "PropertyName": "FocusedBorderColor",
          "RuleProviderType": "Unknown"
        },
        {
          "Category": "Design",
          "PropertyName": "FocusedBorderThickness",
          "RuleProviderType": "Unknown"
        },
        {
          "Category": "Design",
          "PropertyName": "BorderThickness",
          "RuleProviderType": "Unknown"
        },
        {
          "Category": "Design",
          "PropertyName": "LineHeight",
          "RuleProviderType": "Unknown"
        },
        {
          "Category": "Design",
          "PropertyName": "HoverBorderColor",
          "RuleProviderType": "Unknown"
        },
        {
          "Category": "Design",
          "PropertyName": "ZIndex",
          "RuleProviderType": "Unknown"
        },
        {
          "Category": "Design",
          "PropertyName": "DisplayMode",
          "RuleProviderType": "Unknown"
        },
        {
          "Category": "Design",
          "PropertyName": "PaddingLeft",
          "RuleProviderType": "Unknown"
        },
        {
          "Category": "Design",
          "PropertyName": "PaddingBottom",
          "RuleProviderType": "Unknown"
        },
        {
          "Category": "Design",
          "PropertyName": "Height",
          "RuleProviderType": "Unknown"
        },
        {
          "Category": "Design",
          "PropertyName": "X",
          "RuleProviderType": "Unknown"
        },
        {
          "Category": "Design",
          "PropertyName": "PaddingRight",
          "RuleProviderType": "Unknown"
        },
        {
          "Category": "Design",
          "PropertyName": "PaddingTop",
          "RuleProviderType": "Unknown"
        },
        {
          "Category": "Design",
          "PropertyName": "Y",
          "RuleProviderType": "Unknown"
        },
        {
          "Category": "Design",
          "PropertyName": "Strikethrough",
          "RuleProviderType": "Unknown"
        },
        {
          "Category": "Design",
          "PropertyName": "VerticalAlign",
          "RuleProviderType": "Unknown"
        },
        {
          "Category": "Design",
          "PropertyName": "Align",
          "RuleProviderType": "Unknown"
        },
        {
          "Category": "Design",
          "PropertyName": "Underline",
          "RuleProviderType": "Unknown"
        },
        {
          "Category": "Design",
          "PropertyName": "Italic",
          "RuleProviderType": "Unknown"
        },
        {
          "Category": "Design",
          "PropertyName": "FontWeight",
          "RuleProviderType": "Unknown"
        },
        {
          "Category": "Design",
          "PropertyName": "Font",
          "RuleProviderType": "Unknown"
        },
        {
          "Category": "Design",
          "PropertyName": "BorderStyle",
          "RuleProviderType": "Unknown"
        },
        {
          "Category": "Design",
          "PropertyName": "Fill",
          "RuleProviderType": "Unknown"
        },
        {
          "Category": "Design",
          "PropertyName": "Size",
          "RuleProviderType": "Unknown"
        },
        {
          "Category": "Design",
          "PropertyName": "DisabledFill",
          "RuleProviderType": "Unknown"
        },
        {
          "Category": "Design",
          "PropertyName": "DisabledBorderColor",
          "RuleProviderType": "Unknown"
        },
        {
          "Category": "Design",
          "PropertyName": "BorderColor",
          "RuleProviderType": "Unknown"
        },
        {
          "Category": "Design",
          "PropertyName": "DisabledColor",
          "RuleProviderType": "Unknown"
        },
        {
          "Category": "Design",
          "PropertyName": "Color",
          "RuleProviderType": "Unknown"
        },
        {
          "Category": "Design",
          "PropertyName": "PressedBorderColor",
          "RuleProviderType": "Unknown"
        },
        {
          "Category": "Design",
          "PropertyName": "Overflow",
          "RuleProviderType": "Unknown"
        },
        {
          "Category": "Design",
          "PropertyName": "PressedColor",
          "RuleProviderType": "Unknown"
        },
        {
          "Category": "Design",
          "PropertyName": "HoverFill",
          "RuleProviderType": "Unknown"
        },
        {
          "Category": "Design",
          "PropertyName": "HoverColor",
          "RuleProviderType": "Unknown"
        },
        {
          "Category": "Design",
          "PropertyName": "Width",
          "RuleProviderType": "Unknown"
        },
        {
          "Category": "Design",
          "PropertyName": "PressedFill",
          "RuleProviderType": "Unknown"
        },
        {
          "Category": "Behavior",
          "PropertyName": "OnSelect",
          "RuleProviderType": "Unknown"
        }
      ],
      "StyleName": "defaultLabelStyle",
      "Type": "ControlInfo"
    },
    "envvar_flow_lbl": {
      "AllowAccessToGlobals": true,
      "ControlPropertyState": [
        "Live",
        "Overflow",
        {
          "AFDDataSourceName": "",
          "AutoRuleBindingEnabled": false,
          "AutoRuleBindingString": "\"Text\"",
          "InvariantPropertyName": "Text",
          "IsLockable": false,
          "NameMapSourceSchema": "?"
        },
        "Role",
        {
          "AFDDataSourceName": "",
          "AutoRuleBindingEnabled": false,
          "AutoRuleBindingString": "RGBA(51, 51, 51, 1)",
          "InvariantPropertyName": "Color",
          "IsLockable": false,
          "NameMapSourceSchema": "?"
        },
        "DisabledColor",
        "PressedColor",
        "HoverColor",
        "BorderColor",
        "DisabledBorderColor",
        "PressedBorderColor",
        "HoverBorderColor",
        "BorderStyle",
        "FocusedBorderColor",
        {
          "AFDDataSourceName": "",
          "AutoRuleBindingEnabled": false,
          "AutoRuleBindingString": "RGBA(0, 0, 0, 0)",
          "InvariantPropertyName": "Fill",
          "IsLockable": false,
          "NameMapSourceSchema": "?"
        },
        "DisabledFill",
        "PressedFill",
        "HoverFill",
        "Font",
        {
          "AFDDataSourceName": "",
          "AutoRuleBindingEnabled": false,
          "AutoRuleBindingString": "",
          "InvariantPropertyName": "FontWeight",
          "IsLockable": false,
          "NameMapSourceSchema": "?"
        },
        "Align",
        "VerticalAlign",
        {
          "AFDDataSourceName": "",
          "AutoRuleBindingEnabled": false,
          "AutoRuleBindingString": "120",
          "InvariantPropertyName": "X",
          "IsLockable": false,
          "NameMapSourceSchema": "?"
        },
        {
          "AFDDataSourceName": "",
          "AutoRuleBindingEnabled": false,
          "AutoRuleBindingString": "120",
          "InvariantPropertyName": "Y",
          "IsLockable": false,
          "NameMapSourceSchema": "?"
        },
        {
          "AFDDataSourceName": "",
          "AutoRuleBindingEnabled": false,
          "AutoRuleBindingString": "150",
          "InvariantPropertyName": "Width",
          "IsLockable": false,
          "NameMapSourceSchema": "?"
        },
        "Height",
        "DisplayMode",
        "ZIndex",
        "LineHeight",
        "BorderThickness",
        "FocusedBorderThickness",
        "Size",
        "Italic",
        "Underline",
        "Strikethrough",
        "PaddingTop",
        "PaddingRight",
        "PaddingBottom",
        "PaddingLeft"
      ],
      "HasDynamicProperties": false,
      "IsAutoGenerated": false,
      "IsComponentDefinition": false,
      "IsDataControl": false,
      "IsFromScreenLayout": false,
      "IsGroupControl": false,
      "IsLocked": false,
      "LayoutName": "",
      "MetaDataIDKey": "",
      "Name": "envvar_flow_lbl",
      "ParentIndex": 2,
      "PersistMetaDataIDKey": false,
      "Properties": [
        {
          "Category": "Data",
          "PropertyName": "Role",
          "RuleProviderType": "Unknown"
        },
        {
          "Category": "Data",
          "PropertyName": "Text",
          "RuleProviderType": "Unknown"
        },
        {
          "Category": "Data",
          "PropertyName": "Live",
          "RuleProviderType": "Unknown"
        },
        {
          "Category": "Design",
          "PropertyName": "Size",
          "RuleProviderType": "Unknown"
        },
        {
          "Category": "Design",
          "PropertyName": "FocusedBorderThickness",
          "RuleProviderType": "Unknown"
        },
        {
          "Category": "Design",
          "PropertyName": "LineHeight",
          "RuleProviderType": "Unknown"
        },
        {
          "Category": "Design",
          "PropertyName": "Overflow",
          "RuleProviderType": "Unknown"
        },
        {
          "Category": "Design",
          "PropertyName": "Color",
          "RuleProviderType": "Unknown"
        },
        {
          "Category": "Design",
          "PropertyName": "DisabledColor",
          "RuleProviderType": "Unknown"
        },
        {
          "Category": "Design",
          "PropertyName": "PressedFill",
          "RuleProviderType": "Unknown"
        },
        {
          "Category": "Design",
          "PropertyName": "HoverFill",
          "RuleProviderType": "Unknown"
        },
        {
          "Category": "Design",
          "PropertyName": "BorderColor",
          "RuleProviderType": "Unknown"
        },
        {
          "Category": "Design",
          "PropertyName": "DisabledBorderColor",
          "RuleProviderType": "Unknown"
        },
        {
          "Category": "Design",
          "PropertyName": "PressedBorderColor",
          "RuleProviderType": "Unknown"
        },
        {
          "Category": "Design",
          "PropertyName": "HoverBorderColor",
          "RuleProviderType": "Unknown"
        },
        {
          "Category": "Design",
          "PropertyName": "BorderStyle",
          "RuleProviderType": "Unknown"
        },
        {
          "Category": "Design",
          "PropertyName": "FocusedBorderColor",
          "RuleProviderType": "Unknown"
        },
        {
          "Category": "Design",
          "PropertyName": "Fill",
          "RuleProviderType": "Unknown"
        },
        {
          "Category": "Design",
          "PropertyName": "DisabledFill",
          "RuleProviderType": "Unknown"
        },
        {
          "Category": "Design",
          "PropertyName": "PressedColor",
          "RuleProviderType": "Unknown"
        },
        {
          "Category": "Design",
          "PropertyName": "HoverColor",
          "RuleProviderType": "Unknown"
        },
        {
          "Category": "Design",
          "PropertyName": "Font",
          "RuleProviderType": "Unknown"
        },
        {
          "Category": "Design",
          "PropertyName": "FontWeight",
          "RuleProviderType": "Unknown"
        },
        {
          "Category": "Design",
          "PropertyName": "Align",
          "RuleProviderType": "Unknown"
        },
        {
          "Category": "Design",
          "PropertyName": "VerticalAlign",
          "RuleProviderType": "Unknown"
        },
        {
          "Category": "Design",
          "PropertyName": "X",
          "RuleProviderType": "Unknown"
        },
        {
          "Category": "Design",
          "PropertyName": "Y",
          "RuleProviderType": "Unknown"
        },
        {
          "Category": "Design",
          "PropertyName": "Width",
          "RuleProviderType": "Unknown"
        },
        {
          "Category": "Design",
          "PropertyName": "Height",
          "RuleProviderType": "Unknown"
        },
        {
          "Category": "Design",
          "PropertyName": "DisplayMode",
          "RuleProviderType": "Unknown"
        },
        {
          "Category": "Design",
          "PropertyName": "ZIndex",
          "RuleProviderType": "Unknown"
        },
        {
          "Category": "Design",
          "PropertyName": "BorderThickness",
          "RuleProviderType": "Unknown"
        },
        {
          "Category": "Design",
          "PropertyName": "PaddingBottom",
          "RuleProviderType": "Unknown"
        },
        {
          "Category": "Design",
          "PropertyName": "PaddingLeft",
          "RuleProviderType": "Unknown"
        },
        {
          "Category": "Design",
          "PropertyName": "Strikethrough",
          "RuleProviderType": "Unknown"
        },
        {
          "Category": "Design",
          "PropertyName": "PaddingTop",
          "RuleProviderType": "Unknown"
        },
        {
          "Category": "Design",
          "PropertyName": "PaddingRight",
          "RuleProviderType": "Unknown"
        },
        {
          "Category": "Design",
          "PropertyName": "Italic",
          "RuleProviderType": "Unknown"
        },
        {
          "Category": "Design",
          "PropertyName": "Underline",
          "RuleProviderType": "Unknown"
        }
      ],
      "StyleName": "defaultLabelStyle",
      "Type": "ControlInfo"
    },
    "envvar_name": {
      "AllowAccessToGlobals": true,
      "ControlPropertyState": [
        "Live",
        "Overflow",
        {
          "AFDDataSourceName": "",
          "AutoRuleBindingEnabled": false,
          "AutoRuleBindingString": "ThisItem.metaArea",
          "InvariantPropertyName": "Text",
          "IsLockable": false,
          "NameMapSourceSchema": "?"
        },
        "Role",
        "Color",
        "DisabledColor",
        "PressedColor",
        "HoverColor",
        "BorderColor",
        "DisabledBorderColor",
        "PressedBorderColor",
        "HoverBorderColor",
        "BorderStyle",
        "FocusedBorderColor",
        "Fill",
        "DisabledFill",
        "PressedFill",
        "HoverFill",
        "Font",
        "FontWeight",
        "Align",
        "VerticalAlign",
        {
          "AFDDataSourceName": "",
          "AutoRuleBindingEnabled": false,
          "AutoRuleBindingString": "0",
          "InvariantPropertyName": "X",
          "IsLockable": false,
          "NameMapSourceSchema": "?"
        },
        {
          "AFDDataSourceName": "",
          "AutoRuleBindingEnabled": false,
          "AutoRuleBindingString": "1",
          "InvariantPropertyName": "Y",
          "IsLockable": false,
          "NameMapSourceSchema": "?"
        },
        {
          "AFDDataSourceName": "",
          "AutoRuleBindingEnabled": false,
          "AutoRuleBindingString": "150",
          "InvariantPropertyName": "Width",
          "IsLockable": false,
          "NameMapSourceSchema": "?"
        },
        "Height",
        "DisplayMode",
        "OnSelect",
        "ZIndex",
        "LineHeight",
        "BorderThickness",
        "FocusedBorderThickness",
        "Size",
        "Italic",
        "Underline",
        "Strikethrough",
        "PaddingTop",
        "PaddingRight",
        "PaddingBottom",
        "PaddingLeft"
      ],
      "HasDynamicProperties": false,
      "IsAutoGenerated": false,
      "IsComponentDefinition": false,
      "IsDataControl": false,
      "IsFromScreenLayout": false,
      "IsGroupControl": false,
      "IsLocked": false,
      "LayoutName": "",
      "MetaDataIDKey": "",
      "Name": "envvar_name",
      "ParentIndex": 5,
      "PersistMetaDataIDKey": false,
      "Properties": [
        {
          "Category": "Data",
          "PropertyName": "Role",
          "RuleProviderType": "Unknown"
        },
        {
          "Category": "Data",
          "PropertyName": "Text",
          "RuleProviderType": "Unknown"
        },
        {
          "Category": "Data",
          "PropertyName": "Live",
          "RuleProviderType": "Unknown"
        },
        {
          "Category": "Design",
          "PropertyName": "FocusedBorderThickness",
          "RuleProviderType": "Unknown"
        },
        {
          "Category": "Design",
          "PropertyName": "PaddingLeft",
          "RuleProviderType": "Unknown"
        },
        {
          "Category": "Design",
          "PropertyName": "PressedColor",
          "RuleProviderType": "Unknown"
        },
        {
          "Category": "Design",
          "PropertyName": "Color",
          "RuleProviderType": "Unknown"
        },
        {
          "Category": "Design",
          "PropertyName": "Overflow",
          "RuleProviderType": "Unknown"
        },
        {
          "Category": "Design",
          "PropertyName": "PaddingTop",
          "RuleProviderType": "Unknown"
        },
        {
          "Category": "Design",
          "PropertyName": "DisabledColor",
          "RuleProviderType": "Unknown"
        },
        {
          "Category": "Design",
          "PropertyName": "HoverFill",
          "RuleProviderType": "Unknown"
        },
        {
          "Category": "Design",
          "PropertyName": "BorderColor",
          "RuleProviderType": "Unknown"
        },
        {
          "Category": "Design",
          "PropertyName": "DisabledBorderColor",
          "RuleProviderType": "Unknown"
        },
        {
          "Category": "Design",
          "PropertyName": "PressedFill",
          "RuleProviderType": "Unknown"
        },
        {
          "Category": "Design",
          "PropertyName": "FocusedBorderColor",
          "RuleProviderType": "Unknown"
        },
        {
          "Category": "Design",
          "PropertyName": "DisabledFill",
          "RuleProviderType": "Unknown"
        },
        {
          "Category": "Design",
          "PropertyName": "HoverBorderColor",
          "RuleProviderType": "Unknown"
        },
        {
          "Category": "Design",
          "PropertyName": "Fill",
          "RuleProviderType": "Unknown"
        },
        {
          "Category": "Design",
          "PropertyName": "BorderStyle",
          "RuleProviderType": "Unknown"
        },
        {
          "Category": "Design",
          "PropertyName": "PressedBorderColor",
          "RuleProviderType": "Unknown"
        },
        {
          "Category": "Design",
          "PropertyName": "HoverColor",
          "RuleProviderType": "Unknown"
        },
        {
          "Category": "Design",
          "PropertyName": "Font",
          "RuleProviderType": "Unknown"
        },
        {
          "Category": "Design",
          "PropertyName": "FontWeight",
          "RuleProviderType": "Unknown"
        },
        {
          "Category": "Design",
          "PropertyName": "Align",
          "RuleProviderType": "Unknown"
        },
        {
          "Category": "Design",
          "PropertyName": "VerticalAlign",
          "RuleProviderType": "Unknown"
        },
        {
          "Category": "Design",
          "PropertyName": "X",
          "RuleProviderType": "Unknown"
        },
        {
          "Category": "Design",
          "PropertyName": "Y",
          "RuleProviderType": "Unknown"
        },
        {
          "Category": "Design",
          "PropertyName": "Width",
          "RuleProviderType": "Unknown"
        },
        {
          "Category": "Design",
          "PropertyName": "Height",
          "RuleProviderType": "Unknown"
        },
        {
          "Category": "Design",
          "PropertyName": "DisplayMode",
          "RuleProviderType": "Unknown"
        },
        {
          "Category": "Design",
          "PropertyName": "Size",
          "RuleProviderType": "Unknown"
        },
        {
          "Category": "Design",
          "PropertyName": "ZIndex",
          "RuleProviderType": "Unknown"
        },
        {
          "Category": "Design",
          "PropertyName": "Strikethrough",
          "RuleProviderType": "Unknown"
        },
        {
          "Category": "Design",
          "PropertyName": "LineHeight",
          "RuleProviderType": "Unknown"
        },
        {
          "Category": "Design",
          "PropertyName": "Italic",
          "RuleProviderType": "Unknown"
        },
        {
          "Category": "Design",
          "PropertyName": "PaddingBottom",
          "RuleProviderType": "Unknown"
        },
        {
          "Category": "Design",
          "PropertyName": "PaddingRight",
          "RuleProviderType": "Unknown"
        },
        {
          "Category": "Design",
          "PropertyName": "Underline",
          "RuleProviderType": "Unknown"
        },
        {
          "Category": "Design",
          "PropertyName": "BorderThickness",
          "RuleProviderType": "Unknown"
        },
        {
          "Category": "Behavior",
          "PropertyName": "OnSelect",
          "RuleProviderType": "Unknown"
        }
      ],
      "StyleName": "defaultLabelStyle",
      "Type": "ControlInfo"
    },
    "envvar_name_lbl": {
      "AllowAccessToGlobals": true,
      "ControlPropertyState": [
        "Live",
        "Overflow",
        {
          "AFDDataSourceName": "",
          "AutoRuleBindingEnabled": false,
          "AutoRuleBindingString": "\"Text\"",
          "InvariantPropertyName": "Text",
          "IsLockable": false,
          "NameMapSourceSchema": "?"
        },
        "Role",
        {
          "AFDDataSourceName": "",
          "AutoRuleBindingEnabled": false,
          "AutoRuleBindingString": "RGBA(51, 51, 51, 1)",
          "InvariantPropertyName": "Color",
          "IsLockable": false,
          "NameMapSourceSchema": "?"
        },
        "DisabledColor",
        "PressedColor",
        "HoverColor",
        "BorderColor",
        "DisabledBorderColor",
        "PressedBorderColor",
        "HoverBorderColor",
        "BorderStyle",
        "FocusedBorderColor",
        {
          "AFDDataSourceName": "",
          "AutoRuleBindingEnabled": false,
          "AutoRuleBindingString": "RGBA(0, 0, 0, 0)",
          "InvariantPropertyName": "Fill",
          "IsLockable": false,
          "NameMapSourceSchema": "?"
        },
        "DisabledFill",
        "PressedFill",
        "HoverFill",
        "Font",
        {
          "AFDDataSourceName": "",
          "AutoRuleBindingEnabled": false,
          "AutoRuleBindingString": "",
          "InvariantPropertyName": "FontWeight",
          "IsLockable": false,
          "NameMapSourceSchema": "?"
        },
        "Align",
        "VerticalAlign",
        {
          "AFDDataSourceName": "",
          "AutoRuleBindingEnabled": false,
          "AutoRuleBindingString": "100",
          "InvariantPropertyName": "X",
          "IsLockable": false,
          "NameMapSourceSchema": "?"
        },
        {
          "AFDDataSourceName": "",
          "AutoRuleBindingEnabled": false,
          "AutoRuleBindingString": "100",
          "InvariantPropertyName": "Y",
          "IsLockable": false,
          "NameMapSourceSchema": "?"
        },
        {
          "AFDDataSourceName": "",
          "AutoRuleBindingEnabled": false,
          "AutoRuleBindingString": "150",
          "InvariantPropertyName": "Width",
          "IsLockable": false,
          "NameMapSourceSchema": "?"
        },
        "Height",
        "DisplayMode",
        "ZIndex",
        "LineHeight",
        "BorderThickness",
        "FocusedBorderThickness",
        "Size",
        "Italic",
        "Underline",
        "Strikethrough",
        "PaddingTop",
        "PaddingRight",
        "PaddingBottom",
        "PaddingLeft"
      ],
      "HasDynamicProperties": false,
      "IsAutoGenerated": false,
      "IsComponentDefinition": false,
      "IsDataControl": false,
      "IsFromScreenLayout": false,
      "IsGroupControl": false,
      "IsLocked": false,
      "LayoutName": "",
      "MetaDataIDKey": "",
      "Name": "envvar_name_lbl",
      "ParentIndex": 4,
      "PersistMetaDataIDKey": false,
      "Properties": [
        {
          "Category": "Data",
          "PropertyName": "Role",
          "RuleProviderType": "Unknown"
        },
        {
          "Category": "Data",
          "PropertyName": "Text",
          "RuleProviderType": "Unknown"
        },
        {
          "Category": "Data",
          "PropertyName": "Live",
          "RuleProviderType": "Unknown"
        },
        {
          "Category": "Design",
          "PropertyName": "Size",
          "RuleProviderType": "Unknown"
        },
        {
          "Category": "Design",
          "PropertyName": "BorderThickness",
          "RuleProviderType": "Unknown"
        },
        {
          "Category": "Design",
          "PropertyName": "FocusedBorderThickness",
          "RuleProviderType": "Unknown"
        },
        {
          "Category": "Design",
          "PropertyName": "Overflow",
          "RuleProviderType": "Unknown"
        },
        {
          "Category": "Design",
          "PropertyName": "Color",
          "RuleProviderType": "Unknown"
        },
        {
          "Category": "Design",
          "PropertyName": "DisabledColor",
          "RuleProviderType": "Unknown"
        },
        {
          "Category": "Design",
          "PropertyName": "PressedFill",
          "RuleProviderType": "Unknown"
        },
        {
          "Category": "Design",
          "PropertyName": "HoverFill",
          "RuleProviderType": "Unknown"
        },
        {
          "Category": "Design",
          "PropertyName": "BorderColor",
          "RuleProviderType": "Unknown"
        },
        {
          "Category": "Design",
          "PropertyName": "DisabledBorderColor",
          "RuleProviderType": "Unknown"
        },
        {
          "Category": "Design",
          "PropertyName": "PressedBorderColor",
          "RuleProviderType": "Unknown"
        },
        {
          "Category": "Design",
          "PropertyName": "HoverBorderColor",
          "RuleProviderType": "Unknown"
        },
        {
          "Category": "Design",
          "PropertyName": "BorderStyle",
          "RuleProviderType": "Unknown"
        },
        {
          "Category": "Design",
          "PropertyName": "FocusedBorderColor",
          "RuleProviderType": "Unknown"
        },
        {
          "Category": "Design",
          "PropertyName": "Fill",
          "RuleProviderType": "Unknown"
        },
        {
          "Category": "Design",
          "PropertyName": "DisabledFill",
          "RuleProviderType": "Unknown"
        },
        {
          "Category": "Design",
          "PropertyName": "PressedColor",
          "RuleProviderType": "Unknown"
        },
        {
          "Category": "Design",
          "PropertyName": "HoverColor",
          "RuleProviderType": "Unknown"
        },
        {
          "Category": "Design",
          "PropertyName": "Font",
          "RuleProviderType": "Unknown"
        },
        {
          "Category": "Design",
          "PropertyName": "FontWeight",
          "RuleProviderType": "Unknown"
        },
        {
          "Category": "Design",
          "PropertyName": "Align",
          "RuleProviderType": "Unknown"
        },
        {
          "Category": "Design",
          "PropertyName": "VerticalAlign",
          "RuleProviderType": "Unknown"
        },
        {
          "Category": "Design",
          "PropertyName": "X",
          "RuleProviderType": "Unknown"
        },
        {
          "Category": "Design",
          "PropertyName": "Y",
          "RuleProviderType": "Unknown"
        },
        {
          "Category": "Design",
          "PropertyName": "Width",
          "RuleProviderType": "Unknown"
        },
        {
          "Category": "Design",
          "PropertyName": "Height",
          "RuleProviderType": "Unknown"
        },
        {
          "Category": "Design",
          "PropertyName": "DisplayMode",
          "RuleProviderType": "Unknown"
        },
        {
          "Category": "Design",
          "PropertyName": "ZIndex",
          "RuleProviderType": "Unknown"
        },
        {
          "Category": "Design",
          "PropertyName": "LineHeight",
          "RuleProviderType": "Unknown"
        },
        {
          "Category": "Design",
          "PropertyName": "PaddingBottom",
          "RuleProviderType": "Unknown"
        },
        {
          "Category": "Design",
          "PropertyName": "PaddingLeft",
          "RuleProviderType": "Unknown"
        },
        {
          "Category": "Design",
          "PropertyName": "Strikethrough",
          "RuleProviderType": "Unknown"
        },
        {
          "Category": "Design",
          "PropertyName": "PaddingTop",
          "RuleProviderType": "Unknown"
        },
        {
          "Category": "Design",
          "PropertyName": "PaddingRight",
          "RuleProviderType": "Unknown"
        },
        {
          "Category": "Design",
          "PropertyName": "Italic",
          "RuleProviderType": "Unknown"
        },
        {
          "Category": "Design",
          "PropertyName": "Underline",
          "RuleProviderType": "Unknown"
        }
      ],
      "StyleName": "defaultLabelStyle",
      "Type": "ControlInfo"
    },
    "envvar_order": {
      "AllowAccessToGlobals": true,
      "ControlPropertyState": [
        "Live",
        "Overflow",
        {
          "AFDDataSourceName": "",
          "AutoRuleBindingEnabled": false,
          "AutoRuleBindingString": "ThisItem.metaArea",
          "InvariantPropertyName": "Text",
          "IsLockable": false,
          "NameMapSourceSchema": "?"
        },
        "Role",
        "Color",
        "DisabledColor",
        "PressedColor",
        "HoverColor",
        "BorderColor",
        "DisabledBorderColor",
        "PressedBorderColor",
        "HoverBorderColor",
        "BorderStyle",
        "FocusedBorderColor",
        "Fill",
        "DisabledFill",
        "PressedFill",
        "HoverFill",
        "Font",
        "FontWeight",
        "Align",
        "VerticalAlign",
        {
          "AFDDataSourceName": "",
          "AutoRuleBindingEnabled": false,
          "AutoRuleBindingString": "1105",
          "InvariantPropertyName": "X",
          "IsLockable": false,
          "NameMapSourceSchema": "?"
        },
        {
          "AFDDataSourceName": "",
          "AutoRuleBindingEnabled": false,
          "AutoRuleBindingString": "0",
          "InvariantPropertyName": "Y",
          "IsLockable": false,
          "NameMapSourceSchema": "?"
        },
        {
          "AFDDataSourceName": "",
          "AutoRuleBindingEnabled": false,
          "AutoRuleBindingString": "150",
          "InvariantPropertyName": "Width",
          "IsLockable": false,
          "NameMapSourceSchema": "?"
        },
        "Height",
        "DisplayMode",
        "OnSelect",
        "ZIndex",
        "LineHeight",
        "BorderThickness",
        "FocusedBorderThickness",
        "Size",
        "Italic",
        "Underline",
        "Strikethrough",
        "PaddingTop",
        "PaddingRight",
        "PaddingBottom",
        "PaddingLeft"
      ],
      "HasDynamicProperties": false,
      "IsAutoGenerated": false,
      "IsComponentDefinition": false,
      "IsDataControl": false,
      "IsFromScreenLayout": false,
      "IsGroupControl": false,
      "IsLocked": false,
      "LayoutName": "",
      "MetaDataIDKey": "",
      "Name": "envvar_order",
      "ParentIndex": 4,
      "PersistMetaDataIDKey": false,
      "Properties": [
        {
          "Category": "Data",
          "PropertyName": "Live",
          "RuleProviderType": "Unknown"
        },
        {
          "Category": "Data",
          "PropertyName": "Role",
          "RuleProviderType": "Unknown"
        },
        {
          "Category": "Data",
          "PropertyName": "Text",
          "RuleProviderType": "Unknown"
        },
        {
          "Category": "Design",
          "PropertyName": "HoverFill",
          "RuleProviderType": "Unknown"
        },
        {
          "Category": "Design",
          "PropertyName": "Overflow",
          "RuleProviderType": "Unknown"
        },
        {
          "Category": "Design",
          "PropertyName": "X",
          "RuleProviderType": "Unknown"
        },
        {
          "Category": "Design",
          "PropertyName": "Color",
          "RuleProviderType": "Unknown"
        },
        {
          "Category": "Design",
          "PropertyName": "DisabledColor",
          "RuleProviderType": "Unknown"
        },
        {
          "Category": "Design",
          "PropertyName": "PressedFill",
          "RuleProviderType": "Unknown"
        },
        {
          "Category": "Design",
          "PropertyName": "BorderColor",
          "RuleProviderType": "Unknown"
        },
        {
          "Category": "Design",
          "PropertyName": "DisabledBorderColor",
          "RuleProviderType": "Unknown"
        },
        {
          "Category": "Design",
          "PropertyName": "HoverBorderColor",
          "RuleProviderType": "Unknown"
        },
        {
          "Category": "Design",
          "PropertyName": "PressedBorderColor",
          "RuleProviderType": "Unknown"
        },
        {
          "Category": "Design",
          "PropertyName": "BorderStyle",
          "RuleProviderType": "Unknown"
        },
        {
          "Category": "Design",
          "PropertyName": "PressedColor",
          "RuleProviderType": "Unknown"
        },
        {
          "Category": "Design",
          "PropertyName": "Fill",
          "RuleProviderType": "Unknown"
        },
        {
          "Category": "Design",
          "PropertyName": "DisabledFill",
          "RuleProviderType": "Unknown"
        },
        {
          "Category": "Design",
          "PropertyName": "FocusedBorderColor",
          "RuleProviderType": "Unknown"
        },
        {
          "Category": "Design",
          "PropertyName": "Font",
          "RuleProviderType": "Unknown"
        },
        {
          "Category": "Design",
          "PropertyName": "FontWeight",
          "RuleProviderType": "Unknown"
        },
        {
          "Category": "Design",
          "PropertyName": "Align",
          "RuleProviderType": "Unknown"
        },
        {
          "Category": "Design",
          "PropertyName": "VerticalAlign",
          "RuleProviderType": "Unknown"
        },
        {
          "Category": "Design",
          "PropertyName": "Y",
          "RuleProviderType": "Unknown"
        },
        {
          "Category": "Design",
          "PropertyName": "Width",
          "RuleProviderType": "Unknown"
        },
        {
          "Category": "Design",
          "PropertyName": "Height",
          "RuleProviderType": "Unknown"
        },
        {
          "Category": "Design",
          "PropertyName": "DisplayMode",
          "RuleProviderType": "Unknown"
        },
        {
          "Category": "Design",
          "PropertyName": "ZIndex",
          "RuleProviderType": "Unknown"
        },
        {
          "Category": "Design",
          "PropertyName": "LineHeight",
          "RuleProviderType": "Unknown"
        },
        {
          "Category": "Design",
          "PropertyName": "BorderThickness",
          "RuleProviderType": "Unknown"
        },
        {
          "Category": "Design",
          "PropertyName": "FocusedBorderThickness",
          "RuleProviderType": "Unknown"
        },
        {
          "Category": "Design",
          "PropertyName": "Size",
          "RuleProviderType": "Unknown"
        },
        {
          "Category": "Design",
          "PropertyName": "Underline",
          "RuleProviderType": "Unknown"
        },
        {
          "Category": "Design",
          "PropertyName": "Italic",
          "RuleProviderType": "Unknown"
        },
        {
          "Category": "Design",
          "PropertyName": "PaddingRight",
          "RuleProviderType": "Unknown"
        },
        {
          "Category": "Design",
          "PropertyName": "PaddingTop",
          "RuleProviderType": "Unknown"
        },
        {
          "Category": "Design",
          "PropertyName": "Strikethrough",
          "RuleProviderType": "Unknown"
        },
        {
          "Category": "Design",
          "PropertyName": "PaddingLeft",
          "RuleProviderType": "Unknown"
        },
        {
          "Category": "Design",
          "PropertyName": "PaddingBottom",
          "RuleProviderType": "Unknown"
        },
        {
          "Category": "Design",
          "PropertyName": "HoverColor",
          "RuleProviderType": "Unknown"
        },
        {
          "Category": "Behavior",
          "PropertyName": "OnSelect",
          "RuleProviderType": "Unknown"
        }
      ],
      "StyleName": "defaultLabelStyle",
      "Type": "ControlInfo"
    },
    "envvar_order_lbl": {
      "AllowAccessToGlobals": true,
      "ControlPropertyState": [
        "Live",
        "Overflow",
        {
          "AFDDataSourceName": "",
          "AutoRuleBindingEnabled": false,
          "AutoRuleBindingString": "\"Text\"",
          "InvariantPropertyName": "Text",
          "IsLockable": false,
          "NameMapSourceSchema": "?"
        },
        "Role",
        {
          "AFDDataSourceName": "",
          "AutoRuleBindingEnabled": false,
          "AutoRuleBindingString": "RGBA(51, 51, 51, 1)",
          "InvariantPropertyName": "Color",
          "IsLockable": false,
          "NameMapSourceSchema": "?"
        },
        "DisabledColor",
        "PressedColor",
        "HoverColor",
        "BorderColor",
        "DisabledBorderColor",
        "PressedBorderColor",
        "HoverBorderColor",
        "BorderStyle",
        "FocusedBorderColor",
        {
          "AFDDataSourceName": "",
          "AutoRuleBindingEnabled": false,
          "AutoRuleBindingString": "RGBA(0, 0, 0, 0)",
          "InvariantPropertyName": "Fill",
          "IsLockable": false,
          "NameMapSourceSchema": "?"
        },
        "DisabledFill",
        "PressedFill",
        "HoverFill",
        "Font",
        {
          "AFDDataSourceName": "",
          "AutoRuleBindingEnabled": false,
          "AutoRuleBindingString": "",
          "InvariantPropertyName": "FontWeight",
          "IsLockable": false,
          "NameMapSourceSchema": "?"
        },
        "Align",
        "VerticalAlign",
        {
          "AFDDataSourceName": "",
          "AutoRuleBindingEnabled": false,
          "AutoRuleBindingString": "1216",
          "InvariantPropertyName": "X",
          "IsLockable": false,
          "NameMapSourceSchema": "?"
        },
        "Y",
        {
          "AFDDataSourceName": "",
          "AutoRuleBindingEnabled": false,
          "AutoRuleBindingString": "150",
          "InvariantPropertyName": "Width",
          "IsLockable": false,
          "NameMapSourceSchema": "?"
        },
        "Height",
        "DisplayMode",
        "ZIndex",
        "LineHeight",
        "BorderThickness",
        "FocusedBorderThickness",
        "Size",
        "Italic",
        "Underline",
        "Strikethrough",
        "PaddingTop",
        "PaddingRight",
        "PaddingBottom",
        "PaddingLeft"
      ],
      "HasDynamicProperties": false,
      "IsAutoGenerated": false,
      "IsComponentDefinition": false,
      "IsDataControl": false,
      "IsFromScreenLayout": false,
      "IsGroupControl": false,
      "IsLocked": false,
      "LayoutName": "",
      "MetaDataIDKey": "",
      "Name": "envvar_order_lbl",
      "ParentIndex": 3,
      "PersistMetaDataIDKey": false,
      "Properties": [
        {
          "Category": "Data",
          "PropertyName": "Live",
          "RuleProviderType": "Unknown"
        },
        {
          "Category": "Data",
          "PropertyName": "Text",
          "RuleProviderType": "Unknown"
        },
        {
          "Category": "Data",
          "PropertyName": "Role",
          "RuleProviderType": "Unknown"
        },
        {
          "Category": "Design",
          "PropertyName": "Overflow",
          "RuleProviderType": "Unknown"
        },
        {
          "Category": "Design",
          "PropertyName": "Color",
          "RuleProviderType": "Unknown"
        },
        {
          "Category": "Design",
          "PropertyName": "DisabledColor",
          "RuleProviderType": "Unknown"
        },
        {
          "Category": "Design",
          "PropertyName": "HoverColor",
          "RuleProviderType": "Unknown"
        },
        {
          "Category": "Design",
          "PropertyName": "PressedColor",
          "RuleProviderType": "Unknown"
        },
        {
          "Category": "Design",
          "PropertyName": "BorderColor",
          "RuleProviderType": "Unknown"
        },
        {
          "Category": "Design",
          "PropertyName": "DisabledBorderColor",
          "RuleProviderType": "Unknown"
        },
        {
          "Category": "Design",
          "PropertyName": "FocusedBorderColor",
          "RuleProviderType": "Unknown"
        },
        {
          "Category": "Design",
          "PropertyName": "HoverBorderColor",
          "RuleProviderType": "Unknown"
        },
        {
          "Category": "Design",
          "PropertyName": "BorderStyle",
          "RuleProviderType": "Unknown"
        },
        {
          "Category": "Design",
          "PropertyName": "PressedBorderColor",
          "RuleProviderType": "Unknown"
        },
        {
          "Category": "Design",
          "PropertyName": "Fill",
          "RuleProviderType": "Unknown"
        },
        {
          "Category": "Design",
          "PropertyName": "DisabledFill",
          "RuleProviderType": "Unknown"
        },
        {
          "Category": "Design",
          "PropertyName": "HoverFill",
          "RuleProviderType": "Unknown"
        },
        {
          "Category": "Design",
          "PropertyName": "PressedFill",
          "RuleProviderType": "Unknown"
        },
        {
          "Category": "Design",
          "PropertyName": "Font",
          "RuleProviderType": "Unknown"
        },
        {
          "Category": "Design",
          "PropertyName": "FontWeight",
          "RuleProviderType": "Unknown"
        },
        {
          "Category": "Design",
          "PropertyName": "Align",
          "RuleProviderType": "Unknown"
        },
        {
          "Category": "Design",
          "PropertyName": "VerticalAlign",
          "RuleProviderType": "Unknown"
        },
        {
          "Category": "Design",
          "PropertyName": "X",
          "RuleProviderType": "Unknown"
        },
        {
          "Category": "Design",
          "PropertyName": "Y",
          "RuleProviderType": "Unknown"
        },
        {
          "Category": "Design",
          "PropertyName": "Width",
          "RuleProviderType": "Unknown"
        },
        {
          "Category": "Design",
          "PropertyName": "Height",
          "RuleProviderType": "Unknown"
        },
        {
          "Category": "Design",
          "PropertyName": "DisplayMode",
          "RuleProviderType": "Unknown"
        },
        {
          "Category": "Design",
          "PropertyName": "ZIndex",
          "RuleProviderType": "Unknown"
        },
        {
          "Category": "Design",
          "PropertyName": "LineHeight",
          "RuleProviderType": "Unknown"
        },
        {
          "Category": "Design",
          "PropertyName": "BorderThickness",
          "RuleProviderType": "Unknown"
        },
        {
          "Category": "Design",
          "PropertyName": "FocusedBorderThickness",
          "RuleProviderType": "Unknown"
        },
        {
          "Category": "Design",
          "PropertyName": "Size",
          "RuleProviderType": "Unknown"
        },
        {
          "Category": "Design",
          "PropertyName": "Underline",
          "RuleProviderType": "Unknown"
        },
        {
          "Category": "Design",
          "PropertyName": "Italic",
          "RuleProviderType": "Unknown"
        },
        {
          "Category": "Design",
          "PropertyName": "PaddingRight",
          "RuleProviderType": "Unknown"
        },
        {
          "Category": "Design",
          "PropertyName": "PaddingTop",
          "RuleProviderType": "Unknown"
        },
        {
          "Category": "Design",
          "PropertyName": "Strikethrough",
          "RuleProviderType": "Unknown"
        },
        {
          "Category": "Design",
          "PropertyName": "PaddingLeft",
          "RuleProviderType": "Unknown"
        },
        {
          "Category": "Design",
          "PropertyName": "PaddingBottom",
          "RuleProviderType": "Unknown"
        }
      ],
      "StyleName": "defaultLabelStyle",
      "Type": "ControlInfo"
    },
    "envvar_soln": {
      "AllowAccessToGlobals": true,
      "ControlPropertyState": [
        "Live",
        "Overflow",
        {
          "AFDDataSourceName": "",
          "AutoRuleBindingEnabled": false,
          "AutoRuleBindingString": "ThisItem.metaDocSection",
          "InvariantPropertyName": "Text",
          "IsLockable": false,
          "NameMapSourceSchema": "?"
        },
        "Role",
        "Color",
        "DisabledColor",
        "PressedColor",
        "HoverColor",
        "BorderColor",
        "DisabledBorderColor",
        "PressedBorderColor",
        "HoverBorderColor",
        "BorderStyle",
        "FocusedBorderColor",
        "Fill",
        "DisabledFill",
        "PressedFill",
        "HoverFill",
        "Font",
        "FontWeight",
        "Align",
        "VerticalAlign",
        {
          "AFDDataSourceName": "",
          "AutoRuleBindingEnabled": false,
          "AutoRuleBindingString": "203",
          "InvariantPropertyName": "X",
          "IsLockable": false,
          "NameMapSourceSchema": "?"
        },
        {
          "AFDDataSourceName": "",
          "AutoRuleBindingEnabled": false,
          "AutoRuleBindingString": "1",
          "InvariantPropertyName": "Y",
          "IsLockable": false,
          "NameMapSourceSchema": "?"
        },
        {
          "AFDDataSourceName": "",
          "AutoRuleBindingEnabled": false,
          "AutoRuleBindingString": "150",
          "InvariantPropertyName": "Width",
          "IsLockable": false,
          "NameMapSourceSchema": "?"
        },
        "Height",
        "DisplayMode",
        "OnSelect",
        "ZIndex",
        "LineHeight",
        "BorderThickness",
        "FocusedBorderThickness",
        "Size",
        "Italic",
        "Underline",
        "Strikethrough",
        "PaddingTop",
        "PaddingRight",
        "PaddingBottom",
        "PaddingLeft"
      ],
      "HasDynamicProperties": false,
      "IsAutoGenerated": false,
      "IsComponentDefinition": false,
      "IsDataControl": false,
      "IsFromScreenLayout": false,
      "IsGroupControl": false,
      "IsLocked": false,
      "LayoutName": "",
      "MetaDataIDKey": "",
      "Name": "envvar_soln",
      "ParentIndex": 1,
      "PersistMetaDataIDKey": false,
      "Properties": [
        {
          "Category": "Data",
          "PropertyName": "Role",
          "RuleProviderType": "Unknown"
        },
        {
          "Category": "Data",
          "PropertyName": "Text",
          "RuleProviderType": "Unknown"
        },
        {
          "Category": "Data",
          "PropertyName": "Live",
          "RuleProviderType": "Unknown"
        },
        {
          "Category": "Design",
          "PropertyName": "FocusedBorderThickness",
          "RuleProviderType": "Unknown"
        },
        {
          "Category": "Design",
          "PropertyName": "PaddingLeft",
          "RuleProviderType": "Unknown"
        },
        {
          "Category": "Design",
          "PropertyName": "PressedColor",
          "RuleProviderType": "Unknown"
        },
        {
          "Category": "Design",
          "PropertyName": "Color",
          "RuleProviderType": "Unknown"
        },
        {
          "Category": "Design",
          "PropertyName": "Overflow",
          "RuleProviderType": "Unknown"
        },
        {
          "Category": "Design",
          "PropertyName": "PaddingRight",
          "RuleProviderType": "Unknown"
        },
        {
          "Category": "Design",
          "PropertyName": "DisabledColor",
          "RuleProviderType": "Unknown"
        },
        {
          "Category": "Design",
          "PropertyName": "HoverFill",
          "RuleProviderType": "Unknown"
        },
        {
          "Category": "Design",
          "PropertyName": "BorderColor",
          "RuleProviderType": "Unknown"
        },
        {
          "Category": "Design",
          "PropertyName": "DisabledBorderColor",
          "RuleProviderType": "Unknown"
        },
        {
          "Category": "Design",
          "PropertyName": "PressedFill",
          "RuleProviderType": "Unknown"
        },
        {
          "Category": "Design",
          "PropertyName": "FocusedBorderColor",
          "RuleProviderType": "Unknown"
        },
        {
          "Category": "Design",
          "PropertyName": "DisabledFill",
          "RuleProviderType": "Unknown"
        },
        {
          "Category": "Design",
          "PropertyName": "HoverBorderColor",
          "RuleProviderType": "Unknown"
        },
        {
          "Category": "Design",
          "PropertyName": "Fill",
          "RuleProviderType": "Unknown"
        },
        {
          "Category": "Design",
          "PropertyName": "BorderStyle",
          "RuleProviderType": "Unknown"
        },
        {
          "Category": "Design",
          "PropertyName": "PressedBorderColor",
          "RuleProviderType": "Unknown"
        },
        {
          "Category": "Design",
          "PropertyName": "HoverColor",
          "RuleProviderType": "Unknown"
        },
        {
          "Category": "Design",
          "PropertyName": "Font",
          "RuleProviderType": "Unknown"
        },
        {
          "Category": "Design",
          "PropertyName": "FontWeight",
          "RuleProviderType": "Unknown"
        },
        {
          "Category": "Design",
          "PropertyName": "Align",
          "RuleProviderType": "Unknown"
        },
        {
          "Category": "Design",
          "PropertyName": "VerticalAlign",
          "RuleProviderType": "Unknown"
        },
        {
          "Category": "Design",
          "PropertyName": "X",
          "RuleProviderType": "Unknown"
        },
        {
          "Category": "Design",
          "PropertyName": "Y",
          "RuleProviderType": "Unknown"
        },
        {
          "Category": "Design",
          "PropertyName": "Width",
          "RuleProviderType": "Unknown"
        },
        {
          "Category": "Design",
          "PropertyName": "Height",
          "RuleProviderType": "Unknown"
        },
        {
          "Category": "Design",
          "PropertyName": "DisplayMode",
          "RuleProviderType": "Unknown"
        },
        {
          "Category": "Design",
          "PropertyName": "Size",
          "RuleProviderType": "Unknown"
        },
        {
          "Category": "Design",
          "PropertyName": "ZIndex",
          "RuleProviderType": "Unknown"
        },
        {
          "Category": "Design",
          "PropertyName": "PaddingTop",
          "RuleProviderType": "Unknown"
        },
        {
          "Category": "Design",
          "PropertyName": "LineHeight",
          "RuleProviderType": "Unknown"
        },
        {
          "Category": "Design",
          "PropertyName": "Strikethrough",
          "RuleProviderType": "Unknown"
        },
        {
          "Category": "Design",
          "PropertyName": "Underline",
          "RuleProviderType": "Unknown"
        },
        {
          "Category": "Design",
          "PropertyName": "Italic",
          "RuleProviderType": "Unknown"
        },
        {
          "Category": "Design",
          "PropertyName": "PaddingBottom",
          "RuleProviderType": "Unknown"
        },
        {
          "Category": "Design",
          "PropertyName": "BorderThickness",
          "RuleProviderType": "Unknown"
        },
        {
          "Category": "Behavior",
          "PropertyName": "OnSelect",
          "RuleProviderType": "Unknown"
        }
      ],
      "StyleName": "defaultLabelStyle",
      "Type": "ControlInfo"
    },
    "envvar_soln_lbl": {
      "AllowAccessToGlobals": true,
      "ControlPropertyState": [
        "Live",
        "Overflow",
        {
          "AFDDataSourceName": "",
          "AutoRuleBindingEnabled": false,
          "AutoRuleBindingString": "\"Text\"",
          "InvariantPropertyName": "Text",
          "IsLockable": false,
          "NameMapSourceSchema": "?"
        },
        "Role",
        {
          "AFDDataSourceName": "",
          "AutoRuleBindingEnabled": false,
          "AutoRuleBindingString": "RGBA(51, 51, 51, 1)",
          "InvariantPropertyName": "Color",
          "IsLockable": false,
          "NameMapSourceSchema": "?"
        },
        "DisabledColor",
        "PressedColor",
        "HoverColor",
        "BorderColor",
        "DisabledBorderColor",
        "PressedBorderColor",
        "HoverBorderColor",
        "BorderStyle",
        "FocusedBorderColor",
        {
          "AFDDataSourceName": "",
          "AutoRuleBindingEnabled": false,
          "AutoRuleBindingString": "RGBA(0, 0, 0, 0)",
          "InvariantPropertyName": "Fill",
          "IsLockable": false,
          "NameMapSourceSchema": "?"
        },
        "DisabledFill",
        "PressedFill",
        "HoverFill",
        "Font",
        {
          "AFDDataSourceName": "",
          "AutoRuleBindingEnabled": false,
          "AutoRuleBindingString": "",
          "InvariantPropertyName": "FontWeight",
          "IsLockable": false,
          "NameMapSourceSchema": "?"
        },
        "Align",
        "VerticalAlign",
        {
          "AFDDataSourceName": "",
          "AutoRuleBindingEnabled": false,
          "AutoRuleBindingString": "80",
          "InvariantPropertyName": "X",
          "IsLockable": false,
          "NameMapSourceSchema": "?"
        },
        {
          "AFDDataSourceName": "",
          "AutoRuleBindingEnabled": false,
          "AutoRuleBindingString": "80",
          "InvariantPropertyName": "Y",
          "IsLockable": false,
          "NameMapSourceSchema": "?"
        },
        {
          "AFDDataSourceName": "",
          "AutoRuleBindingEnabled": false,
          "AutoRuleBindingString": "150",
          "InvariantPropertyName": "Width",
          "IsLockable": false,
          "NameMapSourceSchema": "?"
        },
        "Height",
        "DisplayMode",
        "ZIndex",
        "LineHeight",
        "BorderThickness",
        "FocusedBorderThickness",
        "Size",
        "Italic",
        "Underline",
        "Strikethrough",
        "PaddingTop",
        "PaddingRight",
        "PaddingBottom",
        "PaddingLeft"
      ],
      "HasDynamicProperties": false,
      "IsAutoGenerated": false,
      "IsComponentDefinition": false,
      "IsDataControl": false,
      "IsFromScreenLayout": false,
      "IsGroupControl": false,
      "IsLocked": false,
      "LayoutName": "",
      "MetaDataIDKey": "",
      "Name": "envvar_soln_lbl",
      "ParentIndex": 0,
      "PersistMetaDataIDKey": false,
      "Properties": [
        {
          "Category": "Data",
          "PropertyName": "Text",
          "RuleProviderType": "Unknown"
        },
        {
          "Category": "Data",
          "PropertyName": "Live",
          "RuleProviderType": "Unknown"
        },
        {
          "Category": "Data",
          "PropertyName": "Role",
          "RuleProviderType": "Unknown"
        },
        {
          "Category": "Design",
          "PropertyName": "ZIndex",
          "RuleProviderType": "Unknown"
        },
        {
          "Category": "Design",
          "PropertyName": "Size",
          "RuleProviderType": "Unknown"
        },
        {
          "Category": "Design",
          "PropertyName": "LineHeight",
          "RuleProviderType": "Unknown"
        },
        {
          "Category": "Design",
          "PropertyName": "Overflow",
          "RuleProviderType": "Unknown"
        },
        {
          "Category": "Design",
          "PropertyName": "X",
          "RuleProviderType": "Unknown"
        },
        {
          "Category": "Design",
          "PropertyName": "Color",
          "RuleProviderType": "Unknown"
        },
        {
          "Category": "Design",
          "PropertyName": "PressedFill",
          "RuleProviderType": "Unknown"
        },
        {
          "Category": "Design",
          "PropertyName": "HoverFill",
          "RuleProviderType": "Unknown"
        },
        {
          "Category": "Design",
          "PropertyName": "DisabledColor",
          "RuleProviderType": "Unknown"
        },
        {
          "Category": "Design",
          "PropertyName": "BorderColor",
          "RuleProviderType": "Unknown"
        },
        {
          "Category": "Design",
          "PropertyName": "PressedBorderColor",
          "RuleProviderType": "Unknown"
        },
        {
          "Category": "Design",
          "PropertyName": "HoverBorderColor",
          "RuleProviderType": "Unknown"
        },
        {
          "Category": "Design",
          "PropertyName": "DisabledBorderColor",
          "RuleProviderType": "Unknown"
        },
        {
          "Category": "Design",
          "PropertyName": "FocusedBorderColor",
          "RuleProviderType": "Unknown"
        },
        {
          "Category": "Design",
          "PropertyName": "FocusedBorderThickness",
          "RuleProviderType": "Unknown"
        },
        {
          "Category": "Design",
          "PropertyName": "BorderStyle",
          "RuleProviderType": "Unknown"
        },
        {
          "Category": "Design",
          "PropertyName": "PressedColor",
          "RuleProviderType": "Unknown"
        },
        {
          "Category": "Design",
          "PropertyName": "HoverColor",
          "RuleProviderType": "Unknown"
        },
        {
          "Category": "Design",
          "PropertyName": "Fill",
          "RuleProviderType": "Unknown"
        },
        {
          "Category": "Design",
          "PropertyName": "DisabledFill",
          "RuleProviderType": "Unknown"
        },
        {
          "Category": "Design",
          "PropertyName": "Font",
          "RuleProviderType": "Unknown"
        },
        {
          "Category": "Design",
          "PropertyName": "FontWeight",
          "RuleProviderType": "Unknown"
        },
        {
          "Category": "Design",
          "PropertyName": "Align",
          "RuleProviderType": "Unknown"
        },
        {
          "Category": "Design",
          "PropertyName": "VerticalAlign",
          "RuleProviderType": "Unknown"
        },
        {
          "Category": "Design",
          "PropertyName": "Y",
          "RuleProviderType": "Unknown"
        },
        {
          "Category": "Design",
          "PropertyName": "Width",
          "RuleProviderType": "Unknown"
        },
        {
          "Category": "Design",
          "PropertyName": "Height",
          "RuleProviderType": "Unknown"
        },
        {
          "Category": "Design",
          "PropertyName": "DisplayMode",
          "RuleProviderType": "Unknown"
        },
        {
          "Category": "Design",
          "PropertyName": "BorderThickness",
          "RuleProviderType": "Unknown"
        },
        {
          "Category": "Design",
          "PropertyName": "PaddingBottom",
          "RuleProviderType": "Unknown"
        },
        {
          "Category": "Design",
          "PropertyName": "PaddingLeft",
          "RuleProviderType": "Unknown"
        },
        {
          "Category": "Design",
          "PropertyName": "Strikethrough",
          "RuleProviderType": "Unknown"
        },
        {
          "Category": "Design",
          "PropertyName": "PaddingTop",
          "RuleProviderType": "Unknown"
        },
        {
          "Category": "Design",
          "PropertyName": "PaddingRight",
          "RuleProviderType": "Unknown"
        },
        {
          "Category": "Design",
          "PropertyName": "Italic",
          "RuleProviderType": "Unknown"
        },
        {
          "Category": "Design",
          "PropertyName": "Underline",
          "RuleProviderType": "Unknown"
        }
      ],
      "StyleName": "defaultLabelStyle",
      "Type": "ControlInfo"
    },
    "envvarmetadata": {
      "AllowAccessToGlobals": true,
      "ControlPropertyState": [
        {
          "AFDDataSourceName": "",
          "AutoRuleBindingEnabled": false,
          "AutoRuleBindingString": "",
          "InvariantPropertyName": "Items",
          "IsLockable": false,
          "NameMapSourceSchema": "?"
        },
        "WrapCount",
        "TemplateSize",
        "TemplatePadding",
        "Layout",
        "Transition",
        "LoadingSpinner",
        "LoadingSpinnerColor",
        "DisplayMode",
        "BorderColor",
        "DisabledBorderColor",
        "PressedBorderColor",
        "HoverBorderColor",
        "BorderStyle",
        "FocusedBorderColor",
        "Fill",
        "DisabledFill",
        "PressedFill",
        "HoverFill",
        {
          "AFDDataSourceName": "",
          "AutoRuleBindingEnabled": false,
          "AutoRuleBindingString": "30",
          "InvariantPropertyName": "X",
          "IsLockable": false,
          "NameMapSourceSchema": "?"
        },
        {
          "AFDDataSourceName": "",
          "AutoRuleBindingEnabled": false,
          "AutoRuleBindingString": "75",
          "InvariantPropertyName": "Y",
          "IsLockable": false,
          "NameMapSourceSchema": "?"
        },
        {
          "AFDDataSourceName": "",
          "AutoRuleBindingEnabled": false,
          "AutoRuleBindingString": "1316",
          "InvariantPropertyName": "Width",
          "IsLockable": false,
          "NameMapSourceSchema": "?"
        },
        {
          "AFDDataSourceName": "",
          "AutoRuleBindingEnabled": false,
          "AutoRuleBindingString": "575",
          "InvariantPropertyName": "Height",
          "IsLockable": false,
          "NameMapSourceSchema": "?"
        },
        "ZIndex"
      ],
      "GalleryTemplateChildName": "galleryTemplate6_2",
      "HasDynamicProperties": false,
      "IsAutoGenerated": false,
      "IsComponentDefinition": false,
      "IsDataControl": false,
      "IsFromScreenLayout": false,
      "IsGroupControl": false,
      "IsLocked": false,
      "LayoutName": "",
      "MetaDataIDKey": "",
      "Name": "envvarmetadata",
      "ParentIndex": 5,
      "PersistMetaDataIDKey": false,
      "Properties": [
        {
          "Category": "Data",
          "PropertyName": "Items",
          "RuleProviderType": "Unknown"
        },
        {
          "Category": "Data",
          "PropertyName": "WrapCount",
          "RuleProviderType": "Unknown"
        },
        {
          "Category": "Design",
          "PropertyName": "HoverBorderColor",
          "RuleProviderType": "Unknown"
        },
        {
          "Category": "Design",
          "PropertyName": "Fill",
          "RuleProviderType": "Unknown"
        },
        {
          "Category": "Design",
          "PropertyName": "Transition",
          "RuleProviderType": "Unknown"
        },
        {
          "Category": "Design",
          "PropertyName": "TemplateSize",
          "RuleProviderType": "Unknown"
        },
        {
          "Category": "Design",
          "PropertyName": "FocusedBorderColor",
          "RuleProviderType": "Unknown"
        },
        {
          "Category": "Design",
          "PropertyName": "LoadingSpinnerColor",
          "RuleProviderType": "Unknown"
        },
        {
          "Category": "Design",
          "PropertyName": "LoadingSpinner",
          "RuleProviderType": "Unknown"
        },
        {
          "Category": "Design",
          "PropertyName": "DisplayMode",
          "RuleProviderType": "Unknown"
        },
        {
          "Category": "Design",
          "PropertyName": "BorderColor",
          "RuleProviderType": "Unknown"
        },
        {
          "Category": "Design",
          "PropertyName": "BorderStyle",
          "RuleProviderType": "Unknown"
        },
        {
          "Category": "Design",
          "PropertyName": "PressedBorderColor",
          "RuleProviderType": "Unknown"
        },
        {
          "Category": "Design",
          "PropertyName": "HoverFill",
          "RuleProviderType": "Unknown"
        },
        {
          "Category": "Design",
          "PropertyName": "DisabledBorderColor",
          "RuleProviderType": "Unknown"
        },
        {
          "Category": "Design",
          "PropertyName": "Width",
          "RuleProviderType": "Unknown"
        },
        {
          "Category": "Design",
          "PropertyName": "PressedFill",
          "RuleProviderType": "Unknown"
        },
        {
          "Category": "Design",
          "PropertyName": "Y",
          "RuleProviderType": "Unknown"
        },
        {
          "Category": "Design",
          "PropertyName": "DisabledFill",
          "RuleProviderType": "Unknown"
        },
        {
          "Category": "Design",
          "PropertyName": "Layout",
          "RuleProviderType": "Unknown"
        },
        {
          "Category": "Design",
          "PropertyName": "X",
          "RuleProviderType": "Unknown"
        },
        {
          "Category": "Design",
          "PropertyName": "TemplatePadding",
          "RuleProviderType": "Unknown"
        },
        {
          "Category": "Design",
          "PropertyName": "ZIndex",
          "RuleProviderType": "Unknown"
        },
        {
          "Category": "Design",
          "PropertyName": "Height",
          "RuleProviderType": "Unknown"
        }
      ],
      "StyleName": "defaultGalleryStyle",
      "Type": "ControlInfo"
    },
    "galleryTemplate6_2": {
      "AllowAccessToGlobals": true,
      "ControlPropertyState": [
        "TemplateFill"
      ],
      "HasDynamicProperties": false,
      "IsAutoGenerated": false,
      "IsComponentDefinition": false,
      "IsDataControl": true,
      "IsFromScreenLayout": false,
      "IsGroupControl": false,
      "IsLocked": false,
      "LayoutName": "",
      "MetaDataIDKey": "",
      "Name": "galleryTemplate6_2",
      "ParentIndex": 0,
      "PersistMetaDataIDKey": false,
      "Properties": [
        {
          "Category": "Design",
          "PropertyName": "TemplateFill",
          "RuleProviderType": "Unknown"
        }
      ],
      "StyleName": "",
      "Type": "ControlInfo"
    },
    "read-only envvar metadata": {
      "AllowAccessToGlobals": true,
      "ControlPropertyState": [
        "Fill",
        "ImagePosition",
        "Height",
        "Width",
        "Size",
        "Orientation",
        "LoadingSpinner",
        "LoadingSpinnerColor"
      ],
      "IsAutoGenerated": false,
      "IsComponentDefinition": false,
      "IsDataControl": false,
      "IsFromScreenLayout": false,
      "IsGroupControl": false,
      "IsLocked": false,
      "LayoutName": "",
      "MetaDataIDKey": "",
      "Name": "read-only envvar metadata",
      "ParentIndex": 0,
      "PersistMetaDataIDKey": false,
      "Properties": [
        {
          "Category": "Design",
          "PropertyName": "Fill",
          "RuleProviderType": "Unknown"
        },
        {
          "Category": "Design",
          "PropertyName": "ImagePosition",
          "RuleProviderType": "Unknown"
        },
        {
          "Category": "Design",
          "PropertyName": "Height",
          "RuleProviderType": "Unknown"
        },
        {
          "Category": "Design",
          "PropertyName": "Width",
          "RuleProviderType": "Unknown"
        },
        {
          "Category": "Design",
          "PropertyName": "Size",
          "RuleProviderType": "Unknown"
        },
        {
          "Category": "Design",
          "PropertyName": "Orientation",
          "RuleProviderType": "Unknown"
        },
        {
          "Category": "Design",
          "PropertyName": "LoadingSpinner",
          "RuleProviderType": "Unknown"
        },
        {
          "Category": "Design",
          "PropertyName": "LoadingSpinnerColor",
          "RuleProviderType": "Unknown"
        }
      ],
      "StyleName": "defaultScreenStyle",
      "Type": "ControlInfo"
    },
    "Rectangle3_2": {
      "AllowAccessToGlobals": true,
      "ControlPropertyState": [
        "Fill",
        "DisabledFill",
        "PressedFill",
        "HoverFill",
        "BorderColor",
        "BorderStyle",
        "FocusedBorderColor",
        "DisplayMode",
        {
          "AFDDataSourceName": "",
          "AutoRuleBindingEnabled": false,
          "AutoRuleBindingString": "40",
          "InvariantPropertyName": "X",
          "IsLockable": false,
          "NameMapSourceSchema": "?"
        },
        {
          "AFDDataSourceName": "",
          "AutoRuleBindingEnabled": false,
          "AutoRuleBindingString": "16",
          "InvariantPropertyName": "Y",
          "IsLockable": false,
          "NameMapSourceSchema": "?"
        },
        {
          "AFDDataSourceName": "",
          "AutoRuleBindingEnabled": false,
          "AutoRuleBindingString": "150",
          "InvariantPropertyName": "Width",
          "IsLockable": false,
          "NameMapSourceSchema": "?"
        },
        {
          "AFDDataSourceName": "",
          "AutoRuleBindingEnabled": false,
          "AutoRuleBindingString": "100",
          "InvariantPropertyName": "Height",
          "IsLockable": false,
          "NameMapSourceSchema": "?"
        },
        "OnSelect",
        "ZIndex",
        "BorderThickness",
        "FocusedBorderThickness"
      ],
      "HasDynamicProperties": false,
      "IsAutoGenerated": false,
      "IsComponentDefinition": false,
      "IsDataControl": false,
      "IsFromScreenLayout": false,
      "IsGroupControl": false,
      "IsLocked": false,
      "LayoutName": "",
      "MetaDataIDKey": "",
      "Name": "Rectangle3_2",
      "ParentIndex": 6,
      "PersistMetaDataIDKey": false,
      "Properties": [
        {
          "Category": "Design",
          "PropertyName": "Fill",
          "RuleProviderType": "Unknown"
        },
        {
          "Category": "Design",
          "PropertyName": "DisabledFill",
          "RuleProviderType": "Unknown"
        },
        {
          "Category": "Design",
          "PropertyName": "PressedFill",
          "RuleProviderType": "Unknown"
        },
        {
          "Category": "Design",
          "PropertyName": "HoverFill",
          "RuleProviderType": "Unknown"
        },
        {
          "Category": "Design",
          "PropertyName": "BorderColor",
          "RuleProviderType": "Unknown"
        },
        {
          "Category": "Design",
          "PropertyName": "BorderStyle",
          "RuleProviderType": "Unknown"
        },
        {
          "Category": "Design",
          "PropertyName": "FocusedBorderColor",
          "RuleProviderType": "Unknown"
        },
        {
          "Category": "Design",
          "PropertyName": "DisplayMode",
          "RuleProviderType": "Unknown"
        },
        {
          "Category": "Design",
          "PropertyName": "X",
          "RuleProviderType": "Unknown"
        },
        {
          "Category": "Design",
          "PropertyName": "Width",
          "RuleProviderType": "Unknown"
        },
        {
          "Category": "Design",
          "PropertyName": "Height",
          "RuleProviderType": "Unknown"
        },
        {
          "Category": "Design",
          "PropertyName": "ZIndex",
          "RuleProviderType": "Unknown"
        },
        {
          "Category": "Design",
          "PropertyName": "BorderThickness",
          "RuleProviderType": "Unknown"
        },
        {
          "Category": "Design",
          "PropertyName": "FocusedBorderThickness",
          "RuleProviderType": "Unknown"
        },
        {
          "Category": "Design",
          "PropertyName": "Y",
          "RuleProviderType": "Unknown"
        },
        {
          "Category": "Behavior",
          "PropertyName": "OnSelect",
          "RuleProviderType": "Unknown"
        }
      ],
      "StyleName": "defaultRectangleStyle",
      "Type": "ControlInfo"
    }
  },
  "TopParentName": "read-only envvar metadata"
}