<?xml version="1.0" encoding="utf-8"?>
<CanvasApp xmlns:xsi="http://www.w3.org/2001/XMLSchema-instance">
  <Name>coe_environmentrequestappadmin_58e3b</Name>
  <AppVersion>2021-10-01T16:00:36Z</AppVersion>
  <Status>Ready</Status>
  <CreatedByClientVersion>3.21091.38.0</CreatedByClientVersion>
  <MinClientVersion>3.21091.38.0</MinClientVersion>
  <Tags>{"primaryDeviceWidth":"1366","primaryDeviceHeight":"768","sienaVersion":"8a2bfba3-23d0-41c0-afef-3b19388d0abc","deviceCapabilities":"","supportsPortrait":"false","supportsLandscape":"true","primaryFormFactor":"Tablet","publisherVersion":"3.21091.38","minimumRequiredApiVersion":"2.2.0","hasComponent":"true","hasUnlockedComponent":"true","isUnifiedRootApp":"false","optimizedForTeamsMeeting":"false"}</Tags>
  <IsCdsUpgraded>0</IsCdsUpgraded>
  <GalleryItemId xsi:nil="true"></GalleryItemId>
  <BackgroundColor>rgba(36, 42, 44, 1)</BackgroundColor>
  <DisplayName>Admin - Environment Request</DisplayName>
  <Description>Admin app for Power Platform resource request management.</Description>
  <CommitMessage></CommitMessage>
  <Publisher></Publisher>
  <AuthorizationReferences>[]</AuthorizationReferences>
  <ConnectionReferences>{"24f241e1-fb35-4965-8c8b-357b6db1b2a6":{"id":"/providers/microsoft.powerapps/apis/shared_powerplatformforadmins","displayName":"Power Platform for Admins","iconUri":"https://connectoricons-prod.azureedge.net/releases/v1.0.1512/1.0.1512.2544/powerplatformforadmins/icon.png","dataSources":["PowerPlatformforAdmins"],"dependencies":[],"dependents":[],"parameterHints":{},"parameterHintsV2":{},"isOnPremiseConnection":false,"bypassConsent":false,"dataSets":{},"apiTier":"Standard","actions":["ListPoliciesV2","GetAdminEnvironment","ListSupportedLocations","ListEnvironmentCurrencies","ListEnvironmentLanguages"]},"fca84456-c98f-49f7-9f89-552359b29e63":{"id":"/providers/microsoft.powerapps/apis/shared_powerappsforappmakers","displayName":"Power Apps for Makers","iconUri":"https://connectoricons-prod.azureedge.net/releases/v1.0.1512/1.0.1512.2544/powerappsforappmakers/icon.png","dataSources":["PowerAppsforMakers"],"dependencies":[],"dependents":[],"parameterHints":{},"parameterHintsV2":{},"isOnPremiseConnection":false,"bypassConsent":false,"dataSets":{},"apiTier":"Standard","actions":["GetConnectors"]},"ae400b4b-90af-4d98-88bc-9df80776878c":{"id":"/providers/microsoft.powerapps/apis/shared_office365users","displayName":"Office 365 Users","iconUri":"https://connectoricons-prod.azureedge.net/releases/v1.0.1510/1.0.1510.2537/office365users/icon.png","dataSources":["Office365Users"],"dependencies":[],"dependents":[],"parameterHints":{},"parameterHintsV2":{},"isOnPremiseConnection":false,"bypassConsent":false,"dataSets":{},"apiTier":"Standard","actions":["MyProfileV2"]},"9b042c2a-7f23-42eb-999b-489d3f713e4b":{"id":"/providers/microsoft.powerapps/apis/shared_office365groups","displayName":"Office 365 Groups","iconUri":"https://connectoricons-prod.azureedge.net/releases/v1.0.1507/1.0.1507.2528/office365groups/icon.png","dataSources":["Office365Groups"],"dependencies":[],"dependents":[],"parameterHints":{},"parameterHintsV2":{},"isOnPremiseConnection":false,"bypassConsent":false,"dataSets":{},"apiTier":"Standard","actions":["ListOwnedGroupsV3"]}}</ConnectionReferences>
  <DatabaseReferences>{"default.cds":{"databaseDetails":{"referenceType":"Environmental","environmentName":"default.cds","overrideValues":{"status":"NotSpecified"}},"dataSources":{"Environment Creation Requests":{"entitySetName":"coe_environmentcreationrequests","logicalName":"coe_environmentcreationrequest"},"Users":{"entitySetName":"systemusers","logicalName":"systemuser"},"PowerApps Connectors":{"entitySetName":"admin_connectors","logicalName":"admin_connector"},"Makers":{"entitySetName":"admin_makers","logicalName":"admin_maker"},"DLP Policy Change Requests":{"entitySetName":"coe_dlppolicychangerequests","logicalName":"coe_dlppolicychangerequest"},"Security Roles":{"entitySetName":"roles","logicalName":"role"},"Teams":{"entitySetName":"teams","logicalName":"team"},"Model-driven Apps":{"entitySetName":"appmodules","logicalName":"appmodule"},"Privileges":{"entitySetName":"privileges","logicalName":"privilege"},"DLP Policies":{"entitySetName":"admin_dlppolicies","logicalName":"admin_dlppolicy"}}}}</DatabaseReferences>
  <CanvasAppType>0</CanvasAppType>
  <BypassConsent>0</BypassConsent>
  <EmbeddedApp xsi:nil="true"></EmbeddedApp>
  <IntroducedVersion>1.0</IntroducedVersion>
  <CdsDependencies xsi:nil="true"></CdsDependencies>
  <IsCustomizable>1</IsCustomizable>
  <BackgroundImageUri>/CanvasApps/coe_environmentrequestappadmin_58e3b_BackgroundImageUri</BackgroundImageUri>
  <DocumentUri>/CanvasApps/coe_environmentrequestappadmin_58e3b_DocumentUri.msapp</DocumentUri>
</CanvasApp>