{
  "AccessibilityLabel": "Accessibility label",
  "HidePersonaDetails": "Hide Persona Details",
  "ImageAlt": "Image Alt",
  "ImageInitials": "Image Initials",
  "ImageUrl": "Image Url",
  "OptionalText": "Optional Text",
  "Persona": "Fluent Persona (1.1.29) Preview",
  "Persona_Desc": "Persona component",
  "PersonaInitialsColor": "Persona Initials Color",
  "PersonaSize": "Persona Size",
  "Presence": "Presence",
  "SecondaryText": "Secondary Text",
  "TertiaryText": "Tertiary Text",
  "Text": "Text",
  "Theme": "Theme"
}